Workbook
Name Slicer_Company: #N/A
Name Slicer_Industry: #N/A
Name Slicer_Industry1: #N/A
Name Slicer_Total_Jobs: #N/A

Sheet postings
A1: job_title | B1: company | C1: job_location | D1: job_link | E1: first_seen | F1: search_city | G1: search_country | H1: job level | I1: job_type | J1: job_summary | K1: job_skills
A2: Data Engineer 2 | B2: Cook Medical | C2: Bloomington, IN | D2: https://www.linkedin.com/jobs/view/data-engineer-2-at-cook-medical-3526207414 | E2: 45277 | F2: Bloomington | G2: United States | H2: Mid senior | I2: Onsite | J2: Overview The Data Engineer develops, implements and documents data systems that provide the technical solutions to meet specifications and business requirements defined by company objectives to promote effective, efficient, and compliant operations. Experience with Azure preferrable. Experience with relational SQL and NoSQL databases; experience with SQL Server, Azure, Oracle, and/or MongoDB preferred. Hybird or Remote position with expectation of Eastern Time Zone Hours. Responsibilities Work as part of a project team to define and document data and data pipelines for a variety of solutions. Technical responsibility for data and data pipelines to ensure compliance with data standards, architectural standards, and achievement of documented requirements. Develop and maintain current state documentation and deliverables for data solutions. Maintain existing and new data solutions to ensure that they continue to meet user needs. Provide assistance to operational teams to ensure continuity of service. Work with the Data Engineering community of practice to identify and implement continuous improvement opportunities. Must have excellent analytical and problem solving skills Performs other duties as assigned Possesses solid working knowledge of subject matter. May provide leadership, coaching, and/or mentoring to a subordinate group. Ability to manage tasks independently and take ownership of responsibilities Performs work under minimal supervision. Demonstrated organizational, analytical and interpersonal skills Must work and interact effectively and professionally with and for others throughout various levels of the global organization Must have effective communication skills and ability to work in a collaborative and independent work situations and environments with minimal supervision Ability to remain calm and receptive in fast paced situations Ability to manage tasks independently; take ownership of responsibilities Qualifications Bachelors Degree in Computer Science or other related degree; or experience of such kind and amount as to provide a comparable background. Experience with relational SQL and NoSQL databases; experience with SQL Server, Oracle, and/or MongoDB preferred. Preferrable 4-6 years of experience as Data Engineer Experience building data transformations, data structures, and data pipelines. Experience with data integration tools. Experience with object-oriented/object function scripting languages. Demonstrated organizational, analytical and interpersonal skills Ability to manage tasks independently; take ownership of responsibilities Physical Requirements Works under general office environment conditions Sitting for extended periods, utilizes close visual acuity for working with computers, equipment, etc. Must be able to perform the essential functions of the job, subject to reasonable accommodation requirements under the ADA Requires occasional early morning or late evening teleconferences International and domestic travel as required For this position, qualified candidates must be legally authorized to be employed in the United States. Cook does not intend to provide sponsorship for employment visa status (e.g., H-1B or TN status) for this employment position. Show more Show less | K2: Azure, SQL, NoSQL, SQL Server, Oracle, MongoDB, Data pipelines, Data integration tools, Objectoriented/object function scripting languages
A3: Staff Data Engineer | B3: Recruiting from Scratch | C3: Bloomington, IN | D3: https://www.linkedin.com/jobs/view/staff-data-engineer-at-recruiting-from-scratch-3744389892 | E3: 45277 | F3: Bloomington | G3: United States | H3: Mid senior | I3: Onsite | J3: This is for a client of Recruiting from Scratch. Who is Recruiting from Scratch: Recruiting from Scratch is a premier talent firm that focuses on placing the best product managers, software, and hardware talent at innovative companies. Our team is 100% remote and we work with teams across the United States to help them hire. We work with companies funded by the best investors including Sequoia Capital, Lightspeed Ventures, Tiger Global Management, A16Z, Accel, DFJ, and more. Our Client: Our client is a dating app. In this role, you will have the opportunity to work with our product teams, building models and APIs to drive new features, deliver analysis to further improve engagement in existing features, and empower our business with real-time insights to drive growth in market share, engagement, and revenue. We see 1 trillion events per year and process 10TB of data daily. What’s the job? Design, develop and deliver data products to production, complying with internal data governance, security and scalability of our system. Solve technical problems of the highest scope and complexity Exert significant influence on the company’s analytical long-range goals and data architecture Define and extend our internal standards for style, maintenance, and best practices for a high-scale data platform Provide mentorship for all on your team to help them grow in their technical responsibilities Propose ideas to improve the scale, performance, and capabilities of the Data Platform Moving implementation to ownership of real-time and batch processing and data governance and policies. Maintain and enforce the business contracts on how data should be represented and stored. Stay on top of new technologies through R&D and prototyping to continuously improve our big data architectures and systems to streamline how we deliver value with high quality to our end users Implementing ETL processes, moving data between systems including S3, Snowflake, Kafka, and Spark. Work closely with our Data Scientists, SREs, and Product Managers to ensure software is high quality and meets user requirements. What We'll Love About You 7+ years of experience working with data at scale, including data engineering, business intelligence, data science, or related field 7+ years experience using Python Experience using big data technologies (Snowflake, Airflow, Kubernetes, Docker, Helm, Spark, pySpark) Significant experience with relational databases and query authoring (SQL) in Snowflake or other distributed Databases Experience with agile engineering practices such as TDD, Pair Programming, Continuous Integration, automated testing, and deployment Experience with building stream-processing systems, using solutions such as Kafka, Storm or Spark-Streaming Experience with dimensional data modeling and schema design in Data Warehouses Familiar with ETL (managing high-quality reliable ETL pipelines) Be familiar with legal compliance (with data management tools) data classification, and retention Location : This role will be located in office twice a week minimum in Palo Alto, San Francisco or Chicago. Salary Range: $180,000 - 250,000 USD base. Equity. Medical, Dental, Vision. https://www.recruitingfromscratch.com/ Show more Show less | K3: Python, Snowflake, Airflow, Kubernetes, Docker, Helm, Spark, pySpark, SQL, TDD, Pair Programming, Continuous Integration, automated testing, Kafka, Storm, SparkStreaming, dimensional data modeling, ETL, data management, data classification
A4: Senior Data Engineer, Public Company | B4: Recruiting from Scratch | C4: Bloomington, IN | D4: https://www.linkedin.com/jobs/view/senior-data-engineer-public-company-at-recruiting-from-scratch-3748828472 | E4: 45277 | F4: Bloomington | G4: United States | H4: Mid senior | I4: Onsite | J4: This is for a client of Recruiting from Scratch. Who is Recruiting from Scratch: Recruiting from Scratch is a premier talent firm that focuses on placing the best product managers, software, and hardware talent at innovative companies. Our team is 100% remote and we work with teams across the United States to help them hire. We work with companies funded by the best investors including Sequoia Capital, Lightspeed Ventures, Tiger Global Management, A16Z, Accel, DFJ, and more. Our Client: Our next evolution is underway as a newly public company looking to expand and continue to build meaningful experiences for our users. From social issues to original content, we’re blazing innovative paths with impact for our community, all while leveraging the latest tech stacks and striving for engineering excellence. At the heart of our work in this new chapter is a shared set of core values: openness and exploration, a bias for action, and strong support of the LGBTQ community. With a track record of strong financial performance and plans for continued headcount growth, we’re looking to build a team of talented, passionate, and open-minded people who believe in our mission, align with our values, and are excited to work at the intersection of innovative technology and social impact. Come be a part of this exciting journey with us. What’s so interesting about this role? Our client is looking to bring on a Senior Data Engineer with chops in cutting edge real-time streaming technologies and ambitions to achieve high quality and reliability with TDD, automation, and continuous delivery. . In this role, you will have the opportunity to work with our product teams, building models and APIs to drive new features, delivers analysis to further improve engagement in existing features, and empowers our business with real-time insights to drive growth in market share, engagement, and revenue. We see 1 trillion events per year and process 10TB of data daily. What’s the job? Design, develop and deliver data products to production, complying with internal data governance, security and scalability of our system. Moving implementation to ownership of real-time and batch processing and data governance and policies. Maintain and enforce the business contracts on how data should be represented and stored. Stay on top of new technologies through R&D and prototyping to continuously improve our big data architectures and systems to streamline how we deliver value with high quality to our end users Implementing ETL processes, moving data between systems including S3, Snowflake, Kafka, and Spark. Work closely with our Data Scientists, SREs, and Product Managers to ensure software is high quality and meets user requirements. What We’ll Love About You 5+ years of experience working with data at scale, including data engineering, business intelligence, data science, or related field. 7+ years experience using Python, Experience using big data technologies (Snowflake, Airflow, Kubernetes, Docker, Helm, Spark, pySpark, ) Significant experience with relational databases and query authoring (SQL) in Snowflake or other distributed Databases. Experience with agile engineering practices such as TDD, Pair Programming, Continuous Integration, automated testing, and deployment. Experience with building stream-processing systems, using solutions such as Kafka, Storm or Spark-Streaming Experience with dimensional data modeling and schema design in Data Warehouses Familiar with ETL (managing high-quality reliable ETL pipelines) Be familiar with legal compliance (with data management tools) data classification, and retention. Location: Palo Alto, San Francisco or Chicago Salary Range: $165,000-$210,000 USD base. Equity. Medical, Dental, Vision. https://www.recruitingfromscratch.com/ Show more Show less | K4: Python, SQL, Snowflake, Airflow, Kubernetes, Docker, Helm, Spark, pySpark, Kafka, Storm, ETL, TDD, Pair programming, Continuous integration, Software testing, Deployment, Streamprocessing systems, Data modeling, Schema design, Data warehouses, Dimensional data modeling, Legal compliance, Data management
A5: Senior Data Engineer, Public Company | B5: Recruiting from Scratch | C5: Bloomington, IN | D5: https://www.linkedin.com/jobs/view/senior-data-engineer-public-company-at-recruiting-from-scratch-3744392289 | E5: 45277 | F5: Bloomington | G5: United States | H5: Mid senior | I5: Onsite | J5: This is for a client of Recruiting from Scratch. Who is Recruiting from Scratch: Recruiting from Scratch is a premier talent firm that focuses on placing the best product managers, software, and hardware talent at innovative companies. Our team is 100% remote and we work with teams across the United States to help them hire. We work with companies funded by the best investors including Sequoia Capital, Lightspeed Ventures, Tiger Global Management, A16Z, Accel, DFJ, and more. Our Client: They are a profitable dating application. Location: This is a hybrid role based in their Chicago office and will require you to be in office Tuesdays and Thursdays. What’s so interesting about this role? Our client is looking to bring on a Senior Data Engineer with chops in cutting edge real-time streaming technologies and ambitions to achieve high quality and reliability with TDD, automation, and continuous delivery. . In this role, you will have the opportunity to work with our product teams, building models and APIs to drive new features, delivers analysis to further improve engagement in existing features, and empowers our business with real-time insights to drive growth in market share, engagement, and revenue. We see 1 trillion events per year and process 10TB of data daily. What’s the job? Design, develop and deliver data products to production, complying with internal data governance, security and scalability of our system. Moving implementation to ownership of real-time and batch processing and data governance and policies. Maintain and enforce the business contracts on how data should be represented and stored. Stay on top of new technologies through R&D and prototyping to continuously improve our big data architectures and systems to streamline how we deliver value with high quality to our end users Implementing ETL processes, moving data between systems including S3, Snowflake, Kafka, and Spark. Work closely with our Data Scientists, SREs, and Product Managers to ensure software is high quality and meets user requirements. What We’ll Love About You 5+ years of experience working with data at scale, including data engineering, business intelligence, data science, or related field. 7+ years experience using Python, Experience using big data technologies (Snowflake, Airflow, Kubernetes, Docker, Helm, Spark, pySpark, ) Significant experience with relational databases and query authoring (SQL) in Snowflake or other distributed Databases. Experience with agile engineering practices such as TDD, Pair Programming, Continuous Integration, automated testing, and deployment. Experience with building stream-processing systems, using solutions such as Kafka, Storm or Spark-Streaming Experience with dimensional data modeling and schema design in Data Warehouses Familiar with ETL (managing high-quality reliable ETL pipelines) Be familiar with legal compliance (with data management tools) data classification, and retention. Location : This role is twice a week in a hybrid role minimum. Salary Range: $165,000-$210,000 USD base. Equity. Medical, Dental, Vision. https://www.recruitingfromscratch.com/ Show more Show less | K5: TDD, Automation, Continuous delivery, Data engineering, Data science, Business intelligence, Python, Snowflake, Airflow, Kubernetes, Docker, Helm, Spark, PySpark, SQL, Agile engineering, Pair programming, Continuous integration, Kafka, Storm, SparkStreaming, Data warehousing, ETL, Data classification, Data retention
A6: Senior Systems Engineer, Azure Data Platform | B6: Cook Medical | C6: Bloomington, IN | D6: https://www.linkedin.com/jobs/view/senior-systems-engineer-azure-data-platform-at-cook-medical-3775650947 | E6: 45277 | F6: Bloomington | G6: United States | H6: Mid senior | I6: Hybrid | J6: Overview We are seeking a talented Azure Cloud and Fabric Data Platform Engineer to play a pivotal role in ensuring the availability, performance, scalability, and security of our Azure-based data environments. In this position, you will collaborate closely with various teams to automate resource provisioning, maintain system integration, and oversee DevOps pipelines. Your responsibilities will include monitoring performance, conducting risk assessments, troubleshooting issues, and optimizing software delivery processes. Additionally, you'll provide technical support, create documentation, and stay updated on emerging technologies. If you are a proactive engineer ready to shape the future of our cloud ecosystem, we invite you to join our dynamic team and contribute to our organization's success. This role is a hybrid position. Candidate must reside within 2 hours via car of the Cook Medical location and is required to work onsite as needed per Manager expectations. For this position, qualified candidates must be legally authorized to be employed in the United States. Cook does not intend to provide sponsorship for employment visa status (e.g., H-1B or TN status) for this employment position. Responsibilities Configure and maintain Azure cloud and Fabric data platform to ensure availability, performance, scalability, and security of development, testing and production environments Communicate with other data team members, cross-IT teams, and key business stakeholders to identify required Azure resources and automate their provisioning Ensure integration with other systems and adherence to IT or business strategies. Serve as liaison with other teams, vendors, consultants, and customer groups to ensure cloud resources and DevOps pipelines are secure, scalable, resilient, monitored, and auditable Monitor overall performance to proactively identify potential issues and tune or improve environment appropriately Perform routine risk assessments for data platform systems and service levels Troubleshoot failed builds and deployments. Determine and fix environment and configuration issues. Analyze logs and communicate potential code issues to development teams Partner with development and cloud engineering teams to optimize the software delivery pipeline, ensuring smooth and efficient releases Provide technical support and troubleshoot issues related to Azure infrastructure, services and deployments to IT development teams Create and maintain technical documentation, guidelines, and DevOps knowledge base articles to facilitate knowledge sharing and collaboration within the team Estimate and manage life-cycle costs and product level roadmaps Stay up to date on new and emerging technologies Evaluate and recommend product standards and new purchases or subscriptions Plan, design, build, test, and implement IT infrastructure systems and technology. Deploy, install, integrate, maintain, and administer systems including hardware, software, and configurations. Lead the planning, life-cycle management, and development for systems. Regularly explore ways to scale, automate, and make service delivery more efficient. Create and maintain technical documentation on designs, engineering procedures, and implementation or operational work products. Work with others to establish and improve processes and procedures. Conduct technology or product exploration, prototypes, and pilots that deliver innovative IT solutions. Evaluate and recommend product standards and new purchases. Drive technical projects by determining scope, managing deliverables, and tracking progress for the creation or deployment of new solutions. Provide decision making, leadership, and coaching or mentoring to others in a group. Demonstrate strong communication skills and ability to thrive in a collaborative and independent environment. Qualifications Minimum four-year technical university degree or equivalent experience; advanced degree preferred. Minimum ten to twelve years of prior relevant work experience. Expert level industry technical certifications. Possess an expert level knowledge of subject matter. Performs work with a high degree of latitude. Handles the most complex issues and escalations from other staff. Physical Requirements Works under general office environment conditions Sitting for extended periods, utilizes close visual acuity for working with computers, equipment, etc. Must be able to perform the essential functions of the job, subject to reasonable accommodation requirements under the ADA Requires occasional early morning or late evening teleconferences International and domestic travel as required This role is a hybrid position. Candidate must reside within 2 hours via car of the Cook Medical location and is required to work onsite as needed per Manager expectations. For this position, qualified candidates must be legally authorized to be employed in the United States. Cook does not intend to provide sponsorship for employment visa status (e.g., H-1B or TN status) for this employment position. Show more Show less
A7: Senior Staff AI Data Engineer | B7: Recruiting from Scratch | C7: Bloomington, IN | D7: https://www.linkedin.com/jobs/view/senior-staff-ai-data-engineer-at-recruiting-from-scratch-3759712024 | E7: 45277 | F7: Bloomington | G7: United States | H7: Mid senior | I7: Hybrid | J7: Who is Recruiting from Scratch : Recruiting from Scratch is a premier talent firm that focuses on placing the best product managers, software, and hardware talent at innovative companies. Our team is 100% remote and we work with teams across the United States to help them hire. We work with companies funded by the best investors including Sequoia Capital, Lightspeed Ventures, Tiger Global Management, A16Z, Accel, DFJ, and more. https://www.recruitingfromscratch.com/ This is a hybrid role based in our Palo Alto, San Francisco or Chicago offices and will require you to be in office Tuesdays and Thursdays. What’s so interesting about this role? We believe that AI can revolutionize the dating industry. Our Data Engineer lead is responsible for building high quality ML datasets at scale, used to train ML models that power AI-centric features. In this pivotal role, you will have the opportunity to build foundational tools and data pipelines to ingest, normalize and clean the valuable data that would be fundamental for our ML engineers to build AI tools including recommendations, LLMs, ads, visual search, growth/notifications, trust and safety. What’s the job? We’re looking for an exceptional data engineer who is passionate about data for AI and values it can bring to our company, Who loves working with data ops at scale; and who is committed to the hard work necessary to continuously improve our ML data pipelines. In this position, you will be responsible for establishing and executing the strategy for our organization’s ML Data Engine, with an initial focus on agile ML Data OPs. This includes identification of infrastructure components and data stack to be used, design and implementation of pipelines between data systems and teams, automation workflows, data enrichment and monitoring tools all for AI models. As a tech lead specialized in data engineering, you are expected to code and contribute to the stack. Responsibilities: Dive into our dataset and design, implement and scale data pre/post processing pipelines of ML models Work on applied ML solutions in the areas of data mining, cleaning, normalizing and modeling Be self-motivated in seeking solutions when the correct path isn’t always known Collaborate with engineers in conceptualizing, planning and implementing data engineering initiatives working with different stakeholders Design and build data platforms & frameworks for processing high volumes of data, in real time as well as batch, that will be used across engineering teams Build data processing streams for cleaning and modeling text data for LLMs Research and evaluate new technologies in the big data space to guide our continuous improvement Collaborate with multi-functional teams to help tune the performance of large data applications Work with Privacy and Security team on data governance, risk and compliance initiatives Work on initiatives to ensure stability, performance and reliability of our data infrastructure What We’ll Love About You Bachelors in Computer Science, Mathematics, Physics, or a related fields 5+ years of experience as a data engineer building production-level pre/post-processing data pipelines for ML/DL models, including 2+ years of technical leadership experience Experience in statistical analysis & visualization on datasets using Pandas or R Experience designing and building highly available, distributed systems of data extraction, ingestion, normalization and processing of large data sets in real time as well as batch, that will be used across engineering teams using orchestration frameworks like Airflow, KubeFlow or other pipeline tools Demonstrated prior experience in creating data pipelines for text data sets NLP/ large language models Ability to produce well-engineered software, including appropriate automated test suites, technical documentation, and operational strategy Excellent coding skills in Python, Java, bash, SQL, and expertise with Git version control Experience using big data technologies (Snowflake, Airflow, Kubernetes, Docker, Helm, Spark, pySpark) Experience with any public cloud environment - AWS, GCP or Azure Significant experience with relational databases and query authoring (SQL) as well as NoSQL databases like DynamoDB etc Experience building and maintaining ETL (managing high-quality reliable ETL pipelines) We’ll really swoon if you have 2+ years of experience of technical leadership in building data engineering pipelines for AI Previous experience in building data pipeline for conversational AI APIs and recommender systems Experience with distributed systems and microservices Experience with Kubernetes and building Docker images Experience with building stream-processing systems, using solutions such as Kafka, Storm or Spark-Streaming Strong understanding of applied machine learning topics Be familiar with legal compliance (with data management tools) data classification, and retention Consistent track record of managing and implementing complex data projects What You'll Love About Us Mission and Impact: We are the world-leading LGBTQ social networking service. Your role will impact the lives of millions of LGBTQ people around the world Multiple Locations: We are hiring someone for this role to be based ideally in San Francisco or Palo Alto Family Insurance: Insurance premium coverage for health, dental, and vision for you and partial coverage for your dependents Retirement Savings: Generous 401K plan with 6% match and immediate vest in the US Compensation: Industry-competitive compensation and eligibility for company bonus and equity programs Queer-Inclusive Benefits: Industry-leading gender-affirming offerings with up to 90% cost coverage, access to Included Health, monthly stipends for HRT, and more Additional Benefits: Flexible vacation policy, monthly stipends for cell phone, internet, wellness, and food, one-time home-office setup stipend, and company-sponsored events Base Pay Range $160,000—$280,000 USD https://www.recruitingfromscratch.com/ Show more Show less | K7: Data Engineering, ML Data Ops, Data Mining, Data Cleaning, Data Normalization, Data Modeling, Data Enrichment, Data Monitoring, Data Platforms, Data Frameworks, Big Data Technologies, Data Pipelines, Machine Learning, Natural Language Processing, Large Language Models, Python, Java, Bash, SQL, Git, Snowflake, Airflow, Kubernetes, Docker, Helm, Spark, PySpark, AWS, GCP, Azure, NoSQL, ETL, Kafka, Storm, SparkStreaming, Applied Machine Learning, Data Management Tools, Data Classification, Data Retention, GenderAffirming Offerings, HR, Health, Dental, Vision
A8: Senior Staff AI Data Engineer | B8: Recruiting from Scratch | C8: Bloomington, IN | D8: https://www.linkedin.com/jobs/view/senior-staff-ai-data-engineer-at-recruiting-from-scratch-3773088678 | E8: 45277 | F8: Bloomington | G8: United States | H8: Mid senior | I8: Hybrid | J8: Who is Recruiting from Scratch : Recruiting from Scratch is a premier talent firm that focuses on placing the best product managers, software, and hardware talent at innovative companies. Our team is 100% remote and we work with teams across the United States to help them hire. We work with companies funded by the best investors including Sequoia Capital, Lightspeed Ventures, Tiger Global Management, A16Z, Accel, DFJ, and more. https://www.recruitingfromscratch.com/ This is a hybrid role based in our Palo Alto or San Francisco offices and will require you to be in office Tuesdays and Thursdays. What’s so interesting about this role? We believe that AI can revolutionize the dating industry. Our Data Engineer lead is responsible for building high quality ML datasets at scale, used to train ML models that power AI-centric features. In this pivotal role, you will have the opportunity to build foundational tools and data pipelines to ingest, normalize and clean the valuable data that would be fundamental for our ML engineers to build AI tools including recommendations, LLMs, ads, visual search, growth/notifications, trust and safety. What’s the job? We’re looking for an exceptional data engineer who is passionate about data for AI and values it can bring to our company, Who loves working with data ops at scale; and who is committed to the hard work necessary to continuously improve our ML data pipelines. In this position, you will be responsible for establishing and executing the strategy for our organization’s ML Data Engine, with an initial focus on agile ML Data OPs. This includes identification of infrastructure components and data stack to be used, design and implementation of pipelines between data systems and teams, automation workflows, data enrichment and monitoring tools all for AI models. As a tech lead specialized in data engineering, you are expected to code and contribute to the stack. Responsibilities: Dive into our dataset and design, implement and scale data pre/post processing pipelines of ML models Work on applied ML solutions in the areas of data mining, cleaning, normalizing and modeling Be self-motivated in seeking solutions when the correct path isn’t always known Collaborate with engineers in conceptualizing, planning and implementing data engineering initiatives working with different stakeholders Design and build data platforms & frameworks for processing high volumes of data, in real time as well as batch, that will be used across engineering teams Build data processing streams for cleaning and modeling text data for LLMs Research and evaluate new technologies in the big data space to guide our continuous improvement Collaborate with multi-functional teams to help tune the performance of large data applications Work with Privacy and Security team on data governance, risk and compliance initiatives Work on initiatives to ensure stability, performance and reliability of our data infrastructure What We’ll Love About You Bachelors in Computer Science, Mathematics, Physics, or a related fields 5+ years of experience as a data engineer building production-level pre/post-processing data pipelines for ML/DL models, including 2+ years of technical leadership experience Experience in statistical analysis & visualization on datasets using Pandas or R Experience designing and building highly available, distributed systems of data extraction, ingestion, normalization and processing of large data sets in real time as well as batch, that will be used across engineering teams using orchestration frameworks like Airflow, KubeFlow or other pipeline tools Demonstrated prior experience in creating data pipelines for text data sets NLP/ large language models Ability to produce well-engineered software, including appropriate automated test suites, technical documentation, and operational strategy Excellent coding skills in Python, Java, bash, SQL, and expertise with Git version control Experience using big data technologies (Snowflake, Airflow, Kubernetes, Docker, Helm, Spark, pySpark) Experience with any public cloud environment - AWS, GCP or Azure Significant experience with relational databases and query authoring (SQL) as well as NoSQL databases like DynamoDB etc Experience building and maintaining ETL (managing high-quality reliable ETL pipelines) We’ll really swoon if you have 2+ years of experience of technical leadership in building data engineering pipelines for AI Previous experience in building data pipeline for conversational AI APIs and recommender systems Experience with distributed systems and microservices Experience with Kubernetes and building Docker images Experience with building stream-processing systems, using solutions such as Kafka, Storm or Spark-Streaming Strong understanding of applied machine learning topics Be familiar with legal compliance (with data management tools) data classification, and retention Consistent track record of managing and implementing complex data projects What You'll Love About Us Mission and Impact: We are the world-leading LGBTQ social networking service. Your role will impact the lives of millions of LGBTQ people around the world Multiple Locations: We are hiring someone for this role to be based ideally in San Francisco or Palo Alto Family Insurance: Insurance premium coverage for health, dental, and vision for you and partial coverage for your dependents Retirement Savings: Generous 401K plan with 6% match and immediate vest in the US Compensation: Industry-competitive compensation and eligibility for company bonus and equity programs Queer-Inclusive Benefits: Industry-leading gender-affirming offerings with up to 90% cost coverage, access to Included Health, monthly stipends for HRT, and more Additional Benefits: Flexible vacation policy, monthly stipends for cell phone, internet, wellness, and food, one-time home-office setup stipend, and company-sponsored events Base Pay Range $160,000—$280,000 USD https://www.recruitingfromscratch.com/ Show more Show less | K8: Data Engineer, ML, Data Ops, Data Pipelines, Data Pre/post Processing, Data Mining, Data Cleaning, Data Normalization, Data Modeling, Data Platforms, Data Frameworks, Big Data, Data Governance, Data Infrastructure, Python, Java, Bash, SQL, Git, Snowflake, Airflow, Kubernetes, Docker, Helm, Spark, PySpark, AWS, GCP, Azure, NoSQL, DynamoDB, ETL, Kafka, Storm, SparkStreaming, Machine Learning, Data Compliance, Data Classification, Data Retention, Data Projects
A9: Data Scientist - National Defense/Python/SQL/AWS/MLOps/Clearances | B9: Motion Recruitment | C9: Laughlin AFB, TX | D9: https://www.linkedin.com/jobs/view/data-scientist-national-defense-python-sql-aws-mlops-clearances-at-motion-recruitment-3732144864 | E9: 45277 | F9: Del Rio | G9: United States | H9: Mid senior | I9: Hybrid | J9: An Artificial Intelligence/National Defense start-up is searching for Data Scientists to join their team. You would be solving complex problems by being a systems-level thinker, all the while transforming the nation’s defense and national security. This team handles abstract problems regarding the public policy surrounding climate change, energy, and national security, among other pressing issues. Some of your responsibilities would include discovering datasets that could help in solution development; curating data, analyzing, and performing quantitative modeling; validating the quality of data, models, and results; deploying and implementing solutions in collaboration with product team; and interacting with the product team on current and upcoming user requirements. Required Skills & Experience Masters or Ph.D. in Sciences, Mathematics or Engineering, especially numerical methods and simulations At least 4 years of professional experience in a Data Scientist position Python (pandas, numpy, scipy, sci-kit learn, etc) SQL / MySQL Cloud computing, preferably in an AWS environment Large-scale data processing and implementing batch processing pipelines in HPC or cloud architecture Active government clearance (secret, top secret, ts/sci - no Poly required) What You Will Be Doing Daily Responsibilities 70% Hands On 30% Team Collaboration The Offer Bonus eligible You Will Receive The Following Benefits Full medical, dental, vision coverage for employee and dependents 401k matching program PTO and Holidays Bonus and other incentive programs Access to mental health program Access to Flexible Spending Accounts for Health Care, Dependent and Commuter Applicants must be currently authorized to work in the US on a full-time basis now and in the future. Possession of at minimum a Secret Clearance is required.** Posted By: Lindsay Troyer Show more Show less | K9: Data Science, Numerical Methods, Simulations, Python, Pandas, Numpy, Scipy, Scikit Learn, SQL, MySQL, Cloud Computing, AWS, LargeScale Data Processing, Batch Processing Pipelines, HPC, Government Clearance, HandsOn Work, Team Collaboration, Bonus Eligibility, Full Medical Dental Vision Coverage, 401k Matching Program, PTO, Holidays, Bonus and Incentive Programs, Mental Health Program, Flexible Spending Accounts
A10: Python Data Engineer | B10: Kforce Inc | C10: Merrimack, NH | D10: https://www.linkedin.com/jobs/view/python-data-engineer-at-kforce-inc-3773539932 | E10: 45277 | F10: Inverell | G10: Australia | H10: Associate | I10: Onsite | J10: Responsibilities Kforce has a client in Merrimack, NH that is seeking a Python Data Engineer. Responsibilities: Handling various forms of unstructured and semi structured data and develop solutions to process these complex data Building data pipelines, API's, back-end services using Python Building containerized applications using docker, Kubernetes Processing and exposing data using AWS technologies like ec2, s3, Lambda, API Gateway, Load Balancers, Auto scaling, etc. Building data ingestion tools using technologies like Python to extract data from Relational Databases/Web Scraping/External API's Development working on Cloud/Big Data technologies Requirements BS in Computer Science or related degree, or equivalent experience 5 years of software development experience with at least 3 years working on Cloud/Big Data technologies Experience handling various forms of unstructured and semi structured data and develop solutions to process these complex data Strength in building data pipelines, API's, back-end services using Python Expertise in building containerized applications using docker, Kubernetes Experience in processing and exposing data using AWS technologies like ec2, s3, Lambda, API Gateway, Load Balancers, Auto scaling, etc. Expertise in building data ingestion tools using technologies like Python to extract data from Relational Databases/Web Scraping/External API's Experience in Snowflake or any MPP and columnar database on the Cloud Experience in CI/CD release automation and deployment (Jenkins, Concourse, CloudFormation, etc.) Snowflake or any MPP and columnar database on the Cloud CI/CD release automation and deployment (Jenkins, Concourse, CloudFormation, etc.) Understanding of overall AWS security services like KMS, IAM, Security groups, etc. Good understanding of overall AWS security services like KMS, IAM, Security groups, etc. Knowledge of Angular, Java and reporting tools like Power BI will be an added advantage The pay range is the lowest to highest compensation we reasonably in good faith believe we would pay at posting for this role. We may ultimately pay more or less than this range. Employee pay is based on factors like relevant education, qualifications, certifications, experience, skills, seniority, location, performance, union contract and business needs. This range may be modified in the future. We offer comprehensive benefits including medical/dental/vision insurance, HSA, FSA, 401(k), and life, disability & ADD insurance to eligible employees. Salaried personnel receive paid time off. Hourly employees are not eligible for paid time off unless required by law. Hourly employees on a Service Contract Act project are eligible for paid sick leave. Note: Pay is not considered compensation until it is earned, vested and determinable. The amount and availability of any compensation remains in Kforce's sole discretion unless and until paid and may be modified in its discretion consistent with the law. This job is not eligible for bonuses, incentives or commissions. Kforce is an Equal Opportunity/Affirmative Action Employer. All qualified applicants will receive consideration for employment without regard to race, color, religion, sex, pregnancy, sexual orientation, gender identity, national origin, age, protected veteran status, or disability status. Salary: $69 - $76 per hour Show more Show less
A11: Senior Health Data Migration Engineer Remote | B11: Steneral Consulting | C11: United States | D11: https://www.linkedin.com/jobs/view/senior-health-data-migration-engineer-remote-at-steneral-consulting-3642379153 | E11: 45277 | F11: Inverell | G11: Australia | H11: Mid senior | I11: Remote
A12: Senior ETL Data Quality Engineer | B12: Wise Skulls | C12: United States | D12: https://www.linkedin.com/jobs/view/senior-etl-data-quality-engineer-at-wise-skulls-3748439902 | E12: 45277 | F12: Inverell | G12: Australia | H12: Mid senior | I12: Remote | J12: Title: Senior ETL Data Quality Engineer Location: Austin, TX; Fortmill, SC (Remote for Now) Duration: 12+ Months (Possibility of Extension) Implementation Partner: Infosys End Client: To be disclosed Jd Must have 9+ Years of Expereince. Must have ETL, SQL, Postgres, Cloud (Snowflake, AWS), Automation (Python or Java), CI/CD. Good to have API. Show more Show less | K12: ETL, SQL, PostgreSQL, Cloud, Snowflake, AWS, Python, Java, CI/CD, API
A13: Senior Engineer, Data | B13: Ensemble Health Partners | C13: United States | D13: https://www.linkedin.com/jobs/view/senior-engineer-data-at-ensemble-health-partners-3780820485 | E13: 45277 | F13: Inverell | G13: Australia | H13: Mid senior | I13: Remote | J13: Thank you for considering a career at Ensemble Health Partners! Ensemble Health Partners is a leading provider of technology-enabled revenue cycle management solutions for health systems, including hospitals and affiliated physician groups. They offer end-to-end revenue cycle solutions as well as a comprehensive suite of point solutions to clients across the country. Ensemble keeps communities healthy by keeping hospitals healthy. We recognize that healthcare requires a human touch, and we believe that every touch should be meaningful. This is why our people are the most important part of who we are. By empowering them to challenge the status quo, we know they will be the difference The Opportunity: As a Senior Data Engineer your role will be to implement the technology strategy for Ensemble data engineering team. You will focus on developing reusable software components, patterns, and tooling to address them. You will influence behaviors through code reviews and hands on design sessions. Your outcomes will be a primary contributor to achieving our long-term strategic goals. Develop, test, deploy, monitor, maintain, and continuously improve scalable data pipelines and builds our new API integrations to support continuing increases in data volume and complexity. Translate product concepts into project commitments that deliver incremental value to our customers frequently and with high quality. Actively contribute to the engineering team through code reviews and hands on design sessions. Implements processes and systems to monitor data quality, ensuring production data is always accurate and available for key stakeholders and business processes that depend on it. Review and recommend architectural patterns for data access and performance that align with the company’s best practices and platforms. Required Minimum Education: 4 year/ Bachelors Degree or equivalent of working experience at the level Preferred Education: Graduate Degree (Masters) Other Knowledge, Skills and Abilities Required: 5+ years of coding experience with Microsoft SQL. 3+ years working with big data technologies including but not limited to Databricks, Apache Spark, Python, Microsoft Azure (Data Factory, Dataflows, Azure Functions, Azure Service Bus) with a willingness and ability to learn new ones. Experience and proficient understanding of MS Azure Data Bricks Experience and proficiency in MS SQL- able to create and perform query and codes. Excellent understanding of engineering fundamentals: testing automation, code reviews, telemetry, iterative delivery and DevOps Experience with polyglot storage architectures including relational, columnar, key-value, graph or equivalent Experience with Delta tables as well as Parquet files stored in ADLS Experience delivering applications using componentized and distributed architectures using event driven patterns Demonstrated ability to communicate effectively to both technical and non-technical, globally distributed audiences Solid foundations in formal architecture, design patterns and best practices Understanding and experience working in a healthcare environment is strongly preferred. Join An Award-winning Company Three-time winner of “Best in KLAS” 2020-2022 2022 Top Workplaces Healthcare Industry Award 2022 Top Workplaces USA Award 2022 Top Workplaces Culture Excellence Awards Innovation Work-Life Flexibility Leadership Purpose + Values Bottom line, we believe in empowering people and giving them the tools and resources needed to thrive. A few of those include: Associate Benefits – We offer a comprehensive benefits package designed to support the physical, emotional, and financial health of you and your family, including healthcare, time off, retirement, and well-being programs. Our Culture – Ensemble is a place where associates can do their best work and be their best selves. We put people first, last and always. Our culture is rooted in collaboration, growth, and innovation. Growth – We invest in your professional development. Each associate will earn a professional certification relevant to their field and can obtain tuition reimbursement. Recognition – We offer quarterly and annual incentive programs for all employees who go beyond and keep raising the bar for themselves and the company. Ensemble Health Partners is an equal employment opportunity employer. It is our policy not to discriminate against any applicant or employee based on race, color, sex, sexual orientation, gender, gender identity, religion, national origin, age, disability, military or veteran status, genetic information or any other basis protected by applicable federal, state, or local laws. Ensemble Health Partners also prohibits harassment of applicants or employees based on any of these protected categories. Ensemble Health Partners provides reasonable accommodations to qualified individuals with disabilities in accordance with the Americans with Disabilities Act and applicable state and local law. If you require accommodation in the application process, please contact TA@ensemblehp.com. EEOC – Know Your Rights FMLA Rights - English La FMLA Español Show more Show less | K13: SQL, Databricks, Apache Spark, Python, Azure Functions, Azure Data Bricks, MS SQL, Azure Service Bus, Azure Data Factory, Azure Dataflows, DevOps, Delta tables, AWS, Parquet files, Healthcare
A14: Senior Data Engineer | B14: Attune | C14: New York, NY | D14: https://www.linkedin.com/jobs/view/senior-data-engineer-at-attune-3711772375 | E14: 45277 | F14: Inverell | G14: Australia | H14: Mid senior | I14: Remote | J14: Attune is making it easier, faster, and more reliable for small businesses to access insurance (think, pizza place down the street or main street store). They all need insurance to protect their businesses, but when it comes time to get a policy, they're bogged down by hundreds of questions, lots of paperwork, and a seemingly never-ending timeline stretching for weeks or months. We are changing all that. By using data and technology expertise to understand risk, automating legacy processes, and creating a better user experience for brokers, we're able to provide policies that are more applicable and more transparent in just minutes. Simply put, we're pushing insurance into the future, focusing on accuracy, speed, and ease. Our mission and our team are growing. In staying true to our values, we've earned our spot on many workplace award lists. Attune is dedicated to creating a diverse team of curious, focused, and motivated people who are excited about changing the future of an entire industry. Job Description As a Senior Data Engineer joining our growing Data team, you will serve as a leader for data engineering - helping maintain our existing data pipelines and internal web applications while also providing guidance and support to other team members and looking for ways to improve our code and architecture to meet our growing data needs. You will also work with team members across the organization to develop and test new pipelines as we launch new products and integrate with third-party data sources. We work with various tools including Python/Pandas, Postgresql, Bash, AWS EC2, and S3. We are always open to using whatever tool is best for the job. Responsibilities: Independently drive improvements and optimization in ETLs and internal apps with a focus on future scalability and performance Serve as a leader/mentor for data engineering, employing and encouraging good software and pipeline development practices Develop automated checks to ensure data quality and integrity Maintain and improve batch ETL jobs - including SQL query optimization, bug fixes and code improvements Work with our data engineers, BI, and other teams across the business to develop/refine ETL processes Understand and answer questions on the data our team maintains & influence business decisions in the process, in partnership with Revenue, Marketing, and Underwriting Qualifications: 5+ years experience in analytics, data science, or data engineering role building & maintaining ETL pipelines Expert Python and Postgresql skills Solid understanding of relational database design and basic query optimization techniques Experience working with/optimizing for medium to large datasets in SQL Experience working with git, and Gitlab or Github Nice to have: Experience with Linux CLI, shell programming Understanding of CI/CD Experience with AWS EC2 and S3 What we offer you: 150-190k per year Flexible PTO Generous parental and caregiver leave 401K match Excellent medical, dental, and vision plans Remote-first culture And more! Show more Show less | K14: Python, Pandas, PostgreSQL, Bash, AWS EC2, S3, SQL, Git, GitLab, Github, Linux, CLI, Shell programming, CI/CD
A15: Sr. Data Software Engineer | B15: Steneral Consulting | C15: United States | D15: https://www.linkedin.com/jobs/view/sr-data-software-engineer-at-steneral-consulting-3733275905 | E15: 45277 | F15: Inverell | G15: Australia | H15: Mid senior | I15: Remote | J15: Job : Sr. Data Software Engineer Location: 100% Remote Duration: 6 month Contract to Hire (USC/ GC Holder ONLY) Top Skills SQL Azure Data Factory DBT ETL work Proven ability to complete projects in a timely manner while clearly measuring progress Strong software engineering fundamentals (data structures, algorithms, async programming patterns, object-oriented design, parallel programming) Strong understanding and demonstrated experience with at least one popular programming language (.NET or Java) and SQL constructs. Experience writing and maintaining frontend client applications, Angular preferred Strong experience with revision control (Git) Experience with cloud-based systems (Azure / AWS / GCP). High level understanding of big data design (data lake, data mesh, data warehouse) and data normalization patterns Demonstrated experience with Queuing technologies (Kafka / SNS / RabbitMQ etc) Demonstrated experience with Metrics, Logging, Monitoring and Alerting tools Strong communication skills Strong experience with use of RESTful APIs High level understanding of HL7 V2.x / FHIR based interface messages. High level understanding of system deployment tasks and technologies. (CI/CD Pipeline, K8s, Terraform). Project/Day To Day Communicate with business leaders to help translate requirements into functional specification Develop broad understanding of business logic and functionality of current systems Analyze and manipulate data by writing and running SQL queries Analyze logs to identify and prevent potential issues from occurring Deliver clean and functional code in accordance with business requirements Consume data from any source, such a flat files, streaming systems, or RESTful APIs Interface with Electronic Health Records Engineer scalable, reliable, and performant systems to manage data Collaborate closely with other Engineers, QA, Scrum master, Product Manager in your team as well as across the organization Build quality systems while expanding offerings to dependent teams Comfortable in multiple roles, from Design and Development to Code Deployment to and monitoring and investigating in production systems. Show more Show less | K15: SQL, Azure, Data Factory, DBT, ETL, Data structures, Algorithms, Async programming, Objectoriented design, Parallel programming, .NET, Java, Angular, Git, Cloudbased systems, Big data design, Data normalization, Queuing technologies, Metrics, Logging, Monitoring, Alerting, RESTful APIs, HL7 V2.x / FHIR, CI/CD Pipeline, K8s, Terraform, Electronic Health Records
A16: Data Analyst || Remote | B16: Steneral Consulting | C16: United States | D16: https://www.linkedin.com/jobs/view/data-analyst-remote-at-steneral-consulting-3673756434 | E16: 45277 | F16: Inverell | G16: Australia | H16: Mid senior | I16: Remote | J16: Can be 100% remote; if someone could come onsite some on the front end of the engagement, that would be ideal to help them get up to speed (could put the person up in a corporate hotel around them in Athens, GA) Need LinkedIn Candidates need to taker a video screen with prime vendor prior to end client submittal Must Have 5+ years' experience Data Analysis & Modeling Working knowledge of the Google Cloud Storage and Google BigQuery Knowledge and familiarity of Google Looker (LookML) and/or Power BI (DAX) Strong ANSI SQL experience (DDL, views, stored procedures) Experience collaborating with data engineers and business users to create realistic solutions to business problems Ability to understand business structure and process to determine what measures and KPI's can be gleaned from existing data Strong ability to articulate and explain situations, issues and solutions to members of the organization not regularly involved in data management Job Description The Data Analyst will be responsible for requirements gathering, data modeling within new and existing components for our client's data ecosystem. He or she will have a thorough understanding of relational databases, as well as reporting & visualization technologies. There will be a focus on using raw and partially refined data to configure models and semantic layers within applicable reporting and business intelligence tools throughout the organization to support strategic initiatives. The candidate will need to be comfortable with engaging different areas of the business to gather requirements, evaluate circumstances, and produce results under the guidance of a senior data architect. Essential Job Functions Author and support data models within the semantic layers of relevant data visualization and BI tools Author and support tables, views, and procedures within relational data warehousing technology to effectively ready data for consumption within relevant BI toolsets Create, support, and distribute reports and visualizations using applicable tools available to our client's brand Display a high level of competence with relevant BI tools (Looker, Power BI, etc.) in such a way that business analysts and other end users have the proper guidance on how to use the technology Research and stay abreast of industry leading technologies that improve business intelligence and create highly usable data models Participate in requirements gathering and brainstorming sessions, and be willing to suggest and provide innovative solutions to complex business problems Partner with various groups throughout the organization to create collaborative solutions to meet business needs Collaborate with other teams within IT to create a cohesive integration of systems and data Validate, massage and clean data from all available sources to ensure the highest degree of accuracy and usability Understand and perform to standards within project plans set forth by leaders of the organization and the Project Management Office Qualifications Working knowledge of the Google Cloud Storage and Google BigQuery Knowledge and familiarity of Google Looker (LookML) and/or Power BI (DAX) Strong ANSI SQL experience (DDL, views, stored procedures) Experience collaborating with data engineers and business users to create realistic solutions to business problems Ability to understand business structure and process to determine what measures and KPI's can be gleaned from existing data Strong ability to articulate and explain situations, issues and solutions to members of the organization not regularly involved in data management Ability to join and contribute effectively to large meetings with individuals from various departments within the organization and at various levels Proficient in common offerings within Office 365 product suite (Word, PowerPoint, Excel) Education And Experience Guidelines Education: Bachelor's degree in Computer Science, Information Systems, Data Science, or related field Experience: 5+ years of experience in Data Analysis and Modeling Show more Show less | K16: Data Analysis, Data Modeling, Google Cloud Storage, Google BigQuery, Google Looker (LookML), Power BI (DAX), ANSI SQL, Relational Databases, Reporting & Visualization Technologies, Business Intelligence Tools, Data Visualization, Data Warehousing, Data Cleaning, Data Validation, Project Management, Office 365 (Word PowerPoint Excel), Business Requirements Gathering, Brainstorming, Problem Solving, Communication, Collaboration, Teamwork
A17: Job Opportunity :: Sr. Data Engineer :: 12 Months Contract to hire :: Fully Remote (Hybrid to Houston, TX) | B17: Steneral Consulting | C17: United States | D17: https://www.linkedin.com/jobs/view/job-opportunity-sr-data-engineer-12-months-contract-to-hire-fully-remote-hybrid-to-houston-tx-at-steneral-consulting-3718993789 | E17: 45277 | F17: Inverell | G17: Australia | H17: Mid senior | I17: Remote | J17: Hi, Hope you are doing well, Please find the requirement below , If you find yourself comfortable with the requirement please reply with your Updated Resume and I will get back to you or I would really appreciate if you can give me a call back at my contact number 302-721-5174 Position: Sr. Data Engineer Location: 100% Remote or Hybrid (Houston, TX) Duration: 12 Months Contract to hire Work Authorization: USC, GC Only Interview: Skype Job Description The Client has expressed a desire for the candidates to be able to work a hybrid 3days a week on-site, but they are willing to consider a remote candidate that has "stellar" skill set . This means , EOG would not have to cross train them into any of the tools being used in their environment. They would also need to have the ability of handling development independently as an individual contributor. As discussed before , this Client does not use large teams on big apps, they use data engineers on individual application issues. If you find a candidate who needs to stay remote like Sai, they have to have everything requested in the description and Over and above what the description requests , candidates would need to handle : Experience in PL/SQL development work experience with Oracle 19 Discuss working experience with tools like Airflow, Git Tell me about your python coding experience and REST API developmen t In your career , do you have any experience with accounting and financial data Data Engineer Consultant for Houston Client, and they can be under a VISA , Green Card or USC. "Typically working on big data and cloud technologies is not going to be helpful to us such as; " Hadoop ecosystem, Bigdata, PySpark, Spark, AWS, GCP, Big Query, Data Warehousing" Please note the following preferred skills as they truly need these to get the Manager's attention: Expert In PL/SQL Development Work Experience With Oracle 19 Must have working experience with tools like Airflow, Git Must have python coding experience and REST API development experience Plus Would Be Experience With Accounting And Financial Data Client would also l ike to see 2 code samples of their best code to gauge their coding style, and they can just show it to Client during the interview, They don't need copies of the code. Interview will be Teams based. They have commented , they don't want to see resumes just with cloud technology experience (like with Azure, AWS, GCS etc), they are not using those at site. Candidates need to have the drive to learn new technologies, and can pick up new technologies rapidly, able to self-manage a growing list of tasks and priorities. Remote or Hybrid: We prefer someone local to Houston, who is willing to come to the office at least 3 days a week. But remote option is ok, if you are able to find great candidates. Thank you and Regards Gaurav Raj Sr. Talent Acquisition Specialist -North America Direct: +1 302-721-5174 gaurav@steneral.com 1007, N Orange St, 4th FL 329, Wilmington, DE 19801 Show more Show less | K17: PL/SQL, Oracle 19, Airflow, Git, Python, REST API, Accounting, Financial data
A18: Data Integration Developer | B18: Steneral Consulting | C18: United States | D18: https://www.linkedin.com/jobs/view/data-integration-developer-at-steneral-consulting-3680019522 | E18: 45277 | F18: Inverell | G18: Australia | H18: Mid senior | I18: Remote | J18: Remote Job Description Oracle, PL/SQL, Azure, NoSQL data integration experience with good .Net framework experience Description Develop data integration process flows, distributed programs and data mappings using .Net framework. Design, develop, document Acomplex processes that consolidate and integrate data Perform development, testing and implementation of Oracle PL/SQL, and miscellaneous Windows and Linux scripts to support data integration needs. Implement data solutions using Azure Cloud data components like Azure Synapse, ADLS Gen 2, Azure ADF, Azure NoSQL Database, etc. Support the business by facilitating the importing, exporting, and integration of data between our enterprise systems and those of our partners Develop data integration processes and follow and contribute to best practices for data integration processes Collaborate with the Data Architecture team to understand and implement load processes for reporting and analytic data structures (data warehouses and data marts) Support the business by facilitating the importing, exporting, and integration of data between our enterprise systems and those of our partners Work with the Data Architects to augment ERD's as changes are developed Develop, maintain, and extend reusable data integration components, per design from senior data integration developers/architects. Ensure all data integration processes are documented and recoverable as it pertains to disaster recovery. Collaborate and be approachable to the team. Provide timely project and task updates to all concerned parties Monitor production data integration jobs and correct failures in a timely manner Create and manage incident reports as they pertain to data integration processes Perform all other duties and special projects as assigned. Education And/or Training Bachelor's degree in Computer Science or equivalent work experience Relevant Work Experience Minimum 4 years of work experience in data integration and/or data warehousing Must have a working knowledge of.NET, C#, APIs, Windows Service, ORM, TDD, Windows scripting Knowledge of implementing data solutions using Azure Cloud data components like Azure Synapse, ADLS Gen 2, Azure ADF, Azure NoSQL Database, etc. is preferred Must have a knowledge of Object-Oriented architecture and Service-Oriented architecture Must have a strong command of SQL, ANSI SQL, and PL/SQL for data integration relating to data warehousing and integration. Must have a proven track record of developing well-structured, maintainable data integration solutions Experience querying and loading dimensional and relational data models in a data warehouse environment is required Strong analytical skills, able to effectively solve problems in a timely manner Show more Show less | K18: Oracle, PL/SQL, Azure, NoSQL, .Net Framework, Data integration, Data mapping, Data warehousing, Data architecture, ERD, Data recovery, C#, APIs, Windows Service, ORM, TDD, Windows scripting, Azure Synapse, ADLS Gen 2, Azure ADF, Azure NoSQL Database, ObjectOriented architecture, ServiceOriented architecture, SQL, ANSI SQL, Data modeling, Data analysis
A19: Lead Azure Data Engineer | B19: Donato Technologies, Inc. | C19: United States | D19: https://www.linkedin.com/jobs/view/lead-azure-data-engineer-at-donato-technologies-inc-3707657523 | E19: 45277 | F19: Inverell | G19: Australia | H19: Mid senior | I19: Remote | J19: Job Title: Lead Azure Data Engineer Location: 100% Remote Duration: 6 Months Contract (Possibility for long term extension) Key Skills: ADF, ADLS, Synapse (Azure Sql Datawarehouse), T-Sql This is a lead level role, someone who has lead a team. Min 10-12+ years' experience. Should be purely focused on Azure Cloud, Microsoft Stack, Data Warehouse experience. Looking for someone who been a BI/Sql/ETL Developer etc.. and moved in to Azure cloud Data engineering. Should have good experience in Azure Data lake, Azure Data Factory, Azure Databricks, Azure Synapse and data warehousing concepts. Description Enterprise Data modelling / Design Azure SQL Data Warehouse (Synapse) T-SQL ( Hands-on experience, writing queries, building stored procs, performance optimization, etc..) ADF / Any Enterprise ETL Tool ADLS / any cloud storage Should be able to understand the technical specifications and able to work independently with minimal or no supervision Must Have Skills Extensive experience providing practical direction within azure native services , implementing data migration and data processing using Azure services: ADLS, Azure Data Factory, Synapse/DW /Azure SQL DB, Fabric. Proven experience with SQL, namely schema design and dimensional data modelling Solid knowledge of data warehouse best practices, development standards and methodologies Strong experience with Azure Cloud on data integration with Databricks Be an independent self-learner with the "let's get this done" approach and ability to work in Fast paced and Dynamic environment Nice-to-Have Skills Basic understanding on ML Studio, AI/ML, MLOps etc. Good to have Event Hub, IOT Hub, Azure Stream Analytics, Azure Analysis Service, Cosmo Db knowledge. Good to have SAP Hana knowledge Intermediate knowledge on Power BI Good to have knowledge in DevOps and CI/CD deployments, Cloud migration methodologies and processes. Show more Show less | K19: Azure Cloud, SQL, TSQL, Data Warehouse, Azure Data Lake, Azure Data Factory, Azure Databricks, Azure Synapse, Enterprise Data Modelling, Azure SQL Data Warehouse (Synapse), ADF, ADLS, Data Migration, Data Processing, Schema Design, Dimensional Data Modelling, Data Warehouse Best Practices, Data Integration, Databricks, ML Studio, AI/ML, MLOps, Event Hub, IOT Hub, Azure Stream Analytics, Azure Analysis Service, Cosmo Db, SAP Hana, Power BI, DevOps, CI/CD Deployments, Cloud Migration Methodologies, Cloud Migration Processes
A20: Data Engineer - Lead | B20: Steneral Consulting | C20: United States | D20: https://www.linkedin.com/jobs/view/data-engineer-lead-at-steneral-consulting-3750175286 | E20: 45277 | F20: Inverell | G20: Australia | H20: Mid senior | I20: Remote | J20: Remote role, someone from GA preferred, if not in GA, then must be from FL, NC, AL, CA, NV, IL, UT, MO, TX, PA, NH, PA Candidates need to take a video screen with prime vendor prior to end client submittal Need 2 strong candidates on this role Need strong knowledge of PySprak. 80% of the role will be using Pyspark. They need to be able to be very hands-on and have experience coding within Pyspark not just enabling the tool. Candidates need to have experience with large-scale projects that take 1-2 years versus small projects or proof of concept. Candidates need to have more thought leadership skills. They have a lot of doers currently and need someone who can help guide the team. Top skills: Pyspark Azure Databricks and/or Data Factory Experience leading and managing offshore teams. ETL Must Have Azure Cloud Azure Data Brick ETL High volumes of data Pyspark Python Experience Leading or managing offshore teams Data en gineer has ownership of designing and developing large scale data solutions. You will have deep technical skills in a variety of technologies to play an important role in developing and delivering proof of concepts and product implementation. Responsibilities Design and develop high performant data ingestion pipelines from multiple sources using Azure Databricks and Azure Data Factory Working with event based streaming technologies to ingest and process data Design and Implement Data Lakehouse Working with other members of the project team to support delivery of additional project components (API interfaces, Search) Evaluating the performance and applicability of multiple tools against customer requirements Working within an Agile delivery / DevOps methodology to deliver proof of concept and production implementation in iterative sprints. Work with contractors to deliver products and services for the bottlers Conduct Pilots with bottlers and measure value Transition successful pilots into commercial applications Ensure design and implementation of technologies that comply with security standards and application architecture principles (in alignment with platform architects and respective review boards) and that consider state of the art data and analytics concepts Review code/solutions developed by team prior to migration to production What makes you a good fit? Strong knowledge of data management principles Experience in building ETL pipelines Hands on experience designing and delivering solutions using the Azure including Azure Storage, Azure Data Factory, PySpark, Python, Databricks, Azure Data Lake, Azure Cosmos DB, Azure Stream Analytics Experience working with structured and unstructured data Experience working in DevOps environment 3+ years of relevant experience Ability to balance high customer orientation and service attitude with business priorities Analytic thinking, and problem-solving skills High energy, with strong will and ambition to learn and work on new things Outstanding proven verbal, written and interpersonal communication skills Ability to adapt quickly to changing product scope and priorities (demand driven) Proven ability to influence and collaborate effectively with cross-functional teams Demonstrates noticeable commitment to foster and preserve a culture of diversity and inclusion by creating environments where people of diverse backgrounds are excited to bring all of who they are and do their best work Constant role model of culture: Integrity, Accountability, Passion, Collaboration, Innovation Bachelor’s degree (or equivalent) Show more Show less | K20: PySpark, Azure Databricks, Azure Data Factory, ETL, Azure Cloud, Python, Data Lakehouse, Agile, DevOps, Azure Storage, Azure Cosmos DB, Azure Stream Analytics, Structured Data, Unstructured Data
A21: Sr Data Engineer | B21: Wise Skulls | C21: United States | D21: https://www.linkedin.com/jobs/view/sr-data-engineer-at-wise-skulls-3642856402 | E21: 45277 | F21: Inverell | G21: Australia | H21: Mid senior | I21: Remote
A22: Urgent Role - Senior Data Engineer || Remote | B22: Steneral Consulting | C22: United States | D22: https://www.linkedin.com/jobs/view/urgent-role-senior-data-engineer-remote-at-steneral-consulting-3696912005 | E22: 45277 | F22: Inverell | G22: Australia | H22: Mid senior | I22: Remote | J22: Job Description Title: Senior Data Engineer Location: Remote Duration: 6+ Months Position Details Senior Data Engineer Role: Contract Duration: Contract position approved for 6 months, with likely extension and/or conversion. Location: MN Preferred-Hybrid, would consider 100% Remote from following approved states; AR, AZ, DE, FL, GA, IA, IL, KS, KY, MD, ME, MI, MN, MO, ND, NE, OK, SD, TN, TX, VA, WI. Description The Senior Data Engineer supports ETL Development. They will be responsible for developing and maintaining ETL process and support multiple lines of Business and IT initiatives. This individual may work independently or collaborate with a smaller group of developers in similar efforts. This position is responsible for technical analysis, design, development, testing, and deployment of IT solutions as needed by business or IT. The senior developer works closely with other subject matter experts to help design and build solutions for a multitude of applications, including batch processing, OLTP, OLAP and data warehouse architecture. The Senior Data Engineer will design, build, implement, and maintain data storage structures and processing pipelines for the extraction, transformation, and loading (ETL) of data from a variety of data sources. Develop robust and scalable solutions that transform data into a useful format for analysis, enhance data flow, and enable efficient, cost-effective consumption and analysis of data. Write complex SQL queries to support analytics needs. Evaluate and recommend tools and technologies for data infrastructure and processing. Minimum Knowledge and Skill Complete working knowledge and skill with ability to be fully proficient in professional field. Bachelor's degree or equivalent experience in related field, plus 5 years of related work experience beyond degree. Requirements For All 3 Positions Informatica ETL on premise and on cloud. Master Data Management experience. Informatica MDM experience a plus. Informatica IDQ/CDQ experience. Snowflake, Python, Spark experience Show more Show less | K22: Data Engineering, ETL Development, Data Storage Structures, Data Processing Pipelines, Data Extraction, Data Transformation, Data Loading, SQL, Informatica ETL, Informatica MDM, Informatica IDQ/CDQ, Snowflake, Python, Spark, Batch Processing, OLTP, OLAP, Data Warehouse Architecture
A23: Founding Data Engineer | B23: Rogo | C23: New York, NY | D23: https://www.linkedin.com/jobs/view/founding-data-engineer-at-rogo-3749759981 | E23: 45277 | F23: Inverell | G23: Australia | H23: Mid senior | I23: Remote | J23: Why Rogo? Rogo will be the biggest Financial Services Artificial Intelligence company in the world. We're creating a category-defining AI company built on top of foundational AI models like GPT-4. Exceptional early users: high-paying contracts with the world's largest investment banks, hedge funds, private equity firms, and consultants. Massive demand: extensive waitlist of firms waiting for deployment. World-class team: we take talent density very seriously. We like working with incredibly smart, driven people. Cutting-edge technology: Work directly with the world's most advanced LLMs, AI, and RAG to build the future of generative AI and redefine finance. Top-of-market cash and equity compensation. Challenges: We are building systems that can automate the most complex knowledge work in the world, e.g., financial analysis, research, due diligence, and more. Creating financial research that's worth paying attention to: aggregating, analyzing, and producing insights from real-time information. Say goodbye to equity research. Dealing with the most sensitive data in the world: client data from the largest financial services companies on earth. Working past the edge of published AI research: tackling problems beyond the complexity of existing AI benchmarks. Unsolved product, architectural, and business problems: natural language interfaces, prohibitively expensive evaluation of models, massive marginal costs, versioning/training/segregating models per task, client, and so on. As a founding Data Engineer at Rogo, you will help build out our real-time data pipelines for millions of unstructured financial documents to feed our financial LLM. It’s cutting-edge data engineering at the AI frontier. Hard Requirements: 3+ years of industry experience as a data engineer Highly proficient with Python and SQL, and an intuitive understanding of multi-threading, multi-processing, asyncio, and other concurrency primitives Experience with at least one of: Postgres, Snowflake or Elasticsearch Experience deploying and monitoring mission-critical ETL pipelines with large and heterogenous datasources Experience working with Apache Airflow Experience with AWS or other cloud environment Bonus Requirements: Experience at a hypergrowth startup Financial Services work experience Experience with Typescript Experience with stream processing Knowledge of Datadog and other Telemetry tooling You'll fit in at Rogo if... You have fun solving hard problems: we're tackling tech/product/business problems that are unsolved. It's super exciting. You like to work hard: we feel lucky to work on these problems, and we enjoy pouring our all into solving them. You care deeply about talent density: we care deeply about working with people who are super smart and motivated. You have eclectic interests: whether you're a sci-fi aficionado, history buff, strategy game guru, policy wonk, or movie trivia expert, you'll find kindred spirits here. Compensation Range: $120K - $160K Show more Show less | K23: Python, SQL, Postgres, Snowflake, Elasticsearch, Apache Airflow, AWS, TypeScript, Stream Processing, Datadog, Telemetry, GPT4, Natural Language Processing, Machine Learning, Financial Analysis, Research, Due Diligence, RealTime Data Pipelines, Financial LLM, Data Engineering, Multithreading, Multiprocessing, Asynchronous Programming, Concurrency Primitives, ETL Pipelines, Large and Heterogeneous Data Sources, Cloud Environment
A24: Staff Data Engineer | B24: Nav Technologies, Inc. | C24: Seattle, WA | D24: https://www.linkedin.com/jobs/view/staff-data-engineer-at-nav-technologies-inc-3775330460 | E24: 45277 | F24: Inverell | G24: Australia | H24: Mid senior | I24: Remote | J24: Nav is democratizing small business financing. In other words, we give small business owners access and control. Yes, this challenges the norm, but it means working with curious, purpose driven, dedicated, and inquisitively smart people who push themselves, our company and the community to the next level (and every level after that). We are the people behind the tech. And when it's good, we look for better. We don't over think the value we bring nor spend time trying to revamp mantras. We also do not come up with some crafty way to tell you who we are and what we offer. We are Nav! Here, you'll gain a wealth of experience, learn the tricks of the trade, and work with winners. All companies say people are connected to their mission but in our case our mission and our people are one – it is a way of being not just a cause you are committed to. And since 2013, Nav has holistically and organically developed its own ideology because Nav can only be Nav. We are seeking an innovative and passionate Data Engineer to join our team. In this role you will be responsible for building the data and reporting infrastructure to power our systems, working with our team of engineers, product managers and designers; helping us create a better experience for the millions of Nav Small business users. You'll also work with our business intelligence and data science teams to improve the data platform, ensuring that the entire company is able to make better data-driven decisions. YOU WILL: Building cool stuff by maintaining and fulfilling a technical data engineering roadmap and vision. Creating data and reporting infrastructure by building and optimizing production-grade data pipelines through the use of continuous integration. Exploring data sets for insight and understanding that will help drive great product changes and priority. Communicating results and findings to company audiences of varying technical ability in a clear, engaging manner. Breaking down complex technical concepts into digestible tid-bits. Supporting self-service data pipeline management (ETL) and self-directed learning process. Addressing competing explanations in result validity, and use formal reasoning approaches to avoid bias and miscommunication. Collaboration with Engineering and Data Analysts to identify and design ways to solve critical business problems and ensure funnel optimization. Ability to design, develop, and maintain scalable, reusable code. WHO YOU ARE: You are a driven data engineer with experience working with big data technologies such as Docker, ECS, S3, Redshift, Kafka, and RDS. You have experience with ETL/ELT and data warehousing using tools such as dbt, Azure Data Factory, Matillion and/or Fivetran You love building data-driven products and have expertise in one or more programming languages (ideally Python). You have strong SQL experience, with expert level skill in Postgres, Snowflake and /or AWS Redshift. You're an Apache Airflow practitioner with experience managing cross-DAG dependencies in Airflow. You know how to implement, advocate, and teach agile practices, and adapt them to your people and circumstances, while working in accordance with data ethics & privacy standards. You can consistently evolve data models & data schema based on business and engineering needs. You've developed and extended design patterns, processes, standards, frameworks and reusable components for use in various data engineering functions and areas. Ability to implement systems for tracking data quality and consistency. You're comfortable working directly with all internal data consumers and are eager to share your work through calibrations and organizational product demos. You are committed to quality! And you're someone who's willing to tackle technical debt and constantly evolving our processes to help nav grow. We'd love it if you have a high level understanding of credit scores, ecommerce, and B2B financing. Inclusion at Nav: At Nav, we celebrate what makes our employees unique because the businesses we serve are progressively diverse and distinctly original. Navericks are diverse, side hustlers, immigrants, veterans, queer, and we push generational boundaries. We are college dropouts, PhDs, special needs parents, allies, pet owners and community leaders. Navericks are human. We are committed to upholding a safe, supportive environment where everyone matters. We are committed to making a better future for all of us. We have created a workplace where people of all backgrounds can express their identities authentically. To put it simply, we want you to be proud to be you. Our Compensation Philosophy is simple but powerful: At Nav, we are transparent about our total rewards, including pay, across all levels and roles. We believe great, enduring relationships are grounded in trust and transparency. Compensation shouldn't be a distraction, and employees should understand how pay and career advancement decisions are made. Providing equal pay for equal work is table stakes for being a great place to work. Gender and ethnic inequity should only be something that our children read about in history books. We believe providing Navricks with company ownership, competitive pay, and a range of meaningful benefits is the start of creating a culture where people want to give the best they've got — not because they're simply making money, but because they've fallen in love with our vision, mission, values, and team. During the interview process, your recruiter will be explaining how our rubrics work across all of our total rewards ( base, equity, bonus, perks, and benefit) offerings . The base salary for this role is targeted between $140K - $155K per year. Final offer amount is determined by your proficiencies within this level. Our impact on you: Competitive Pay. Company Ownership. Unlimited Vacation. Benefits Day One. 6 Weeks Paid Parental Leave. Work From Anywhere (yes we were distributed before it was cool). Flexible Work Arrangements. Free Telehealth and Telemental Health For All Employees. Employee Networking and Events. Community Network Groups (women's, PRIDE, culture). Meaningful Perks and Rewards. Learning and Development Opportunities. Pet Insurance. A Naverick's DNA: We look at the future and say "why not"; we see possibilities where others see problems or routines. We show the way ahead and are committed to achieving ambitious goals. We practice straight talk and listen generously to each other with empathy. We value different opinions and point of views. We ensure that we connect outside as well as inside to learn from others and inspire each other. We hold ourselves accountable for delivering results. We choose to not to be a victim of circumstance. We make decisions & take responsibility so that we can act & support each other, rather than adopting defensive, and "finger pointing" behaviors. As leaders we motivate & engage our teams to undertake beyond what they originally thought possible, by developing our teams & creating the conditions for people to grow and empower themselves through enabling & coaching. If you are based in California, we encourage you to read our privacy notice for California residents linked here. Show more Show less | K24: Docker, ECS, S3, Redshift, Kafka, RDS, dbt, Azure Data Factory, Matillion, Fivetran, Python, Postgres, Snowflake, Apache Airflow, Apache Kafka, Tableau, dbt, Fivetran, Matillion, Azure Data Factory, AWS Glue, AWS Redshift, AWS Athena, AWS EMR, AWS SageMaker, Spark, Hadoop, Hive, Pig, Scala, Java, Linux, Unix, Bash, SQL, NoSQL, MongoDB, Cassandra, HBase, Redis, ElasticSearch, Kibana, Logstash, Apache NiFi, Apache Hadoop, Apache Storm, Apache Spark, Apache Flink, Apache Airflow, Apache Hive, Apache Pig, Apache HBase, Apache Phoenix, Apache Cassandra, Apache Kafka, Apache ZooKeeper, Apache Flume, Apache Sqoop, Apache Parquet, Apache Avro, Apache Thrift, Apache Arrow, Apache Impala, Apache Drill, Apache HCatalog, Apache Hive LLAP, Apache Phoenix, Apache Spark SQL, Apache Flink SQL, Apache Beam, Apache Druid, Apache Kylin, Apache Pinot, Apache Superset, Apache Zeppelin, Apache Ambari, Apache Ranger, Apache Atlas, Apache Hive Metastore, Apache Spark Streaming, Apache Flink Streaming, Apache Storm Streaming, Apache Samza, Apache Apex, Apache NiFi Streaming, Apache Kafka Streams, Apache Pulsar, Apache RocketMQ, Apache FlinkCEP, Apache Storm Trident, Apache Samza Streams, Apache Apex Streams, Apache NiFi Streaming, Apache Kafka Streams, Apache Pulsar, Apache RocketMQ, Apache Spark MLlib, Apache Flink ML, Apache Mahout, Apache MxNet, Apache TensorFlow, Apache PyTorch, Apache Keras, Apache Theano, Apache CNTK, Apache MXNet, Apache TVM, Apache Ray, Apache Spark MLlib, Apache Flink ML, Apache Mahout, Apache MxNet, Apache TensorFlow, Apache PyTorch, Apache Keras, Apache Theano, Apache CNTK, Apache MXNet, Apache TVM, Apache Ray
A25: Healthcare Data Analyst | B25: Pasito | C25: United States | D25: https://www.linkedin.com/jobs/view/healthcare-data-analyst-at-pasito-3767238322 | E25: 45277 | F25: Inverell | G25: Australia | H25: Mid senior | I25: Remote | J25: About Pasito Pasito uses data and AI to engage people with their health and financial employee benefits. We integrate payroll, financial, and claims data to personalize employee benefits support and proactively reach employees with benefits communications that drive cost savings for them and their employers. Pasito is backed by Y Combinator and Google. Healthcare Data Analyst We are looking for a Healthcare Data Analyst consultant to collaborate closely with Pasito’s Product and Engineering teams. This is an exciting opportunity to work with leading AI engineers disrupting healthcare for the benefit of families and employees around the country. Pasito is open to structuring a full-time role for the right candidate. As a Health Data Analyst, You Will Review and analyze historical medical claims, accurately mapping CPT codes to specific services, procedures, and diagnoses. Identify trends and patterns in claims data to understand population health, healthcare utilization and cost drivers. Utilize predictive modeling and data analytics techniques to forecast future claims expenses and estimate the impact of various healthcare scenarios, and work closely with Pasito’s engineering team to scale your models. Provide data-driven insights and recommendations for managing claims expenses effectively. Monitor the effectiveness of cost-saving strategies. Build-out real-time reporting (both tabular and visual) Work with engineering teams to streamline data collection and data cleansing Communicate complex healthcare data and findings to non-technical stakeholders in a clear and understandable manner. Create and maintain documentation for data processes and analysis. Support the company's sales and marketing efforts with data analytics. Technical & Interpersonal Skills Bachelor’s degree in Actuarial Science, Mathematics, other physical science, or related finance/business degree required 5+ years of relevant, professional work experience and/or education required Comprehensive understanding of actuarial principles and methodologies and strong mathematical and analytical skills required Comprehensive knowledge of the U.S. benefits landscape, US healthcare and/or US insurance landscape Proficiency with relational databases, data architecture, data visualization tools and libraries. Knowledge of machine learning techniques and algorithms. Excellent English communication skills, both written and verbal. Self-motivated and able to work both independently and collaboratively in a fast-paced environment. Location Remote Show more Show less | K25: Data Analysis, Machine Learning, Actuarial Science, Forecasting, Predictive Modeling, Healthcare, Claims Data, CPT Codes, U.S. Benefits, U.S. Healthcare, U.S. Insurance, Data Architecture, Data Visualization, Relational Databases, Communication Skills, English
A26: Data Engineer( Informatica power Center and Data Stage EXP) | B26: Innovee Consulting LLC | C26: United States | D26: https://www.linkedin.com/jobs/view/data-engineer-informatica-power-center-and-data-stage-exp-at-innovee-consulting-llc-3785705659 | E26: 45277 | F26: Inverell | G26: Australia | H26: Mid senior | I26: Remote | J26: Role: Sr.Data Engineer Informatica power Center and Data Stage EXP) Location: Remote Duration: Long Term The Sr. data engineer will play a pivotal role in designing, building and operationalizing data pipelines that feed the enterprise data ecosystem for a variety of multi-faceted analytics created by data consumers. The data engineer needs to guarantee compliance with data governance and data security requirements while creating, improving and operationalizing integrated and reusable data pipelines. The data engineer will be measured on their ability to create repeatable, efficient, high-quality code, automation-friendly processes, and delivering work products quickly. General Tasks And Responsibilities Will Include Lead construction, maintenance, & optimization of data pipelines. Drive Automation through effective metadata management, using innovative and modern tools, techniques, and architectures to improve productivity. Lead renovation of the data management infrastructure to drive automation in data integration and management. Collaborate with multiple Analytics Center of Excellence teams and EIM team in refining their data requirements for various DnA initiatives and data consumption requirements. Identify gaps in new data initiatives and how to address new data requirements. Transfer knowledge of data and/or domain understanding in addressing new data requirements. Propose appropriate (and innovative) data ingestion, preparation, integration and operationalization techniques to optimize data requirements. Work with data governance teams to ensure data scientists and consumers use corresponding data responsibly through data governance and compliance initiatives. Design and implement data quality monitoring systems, which includes source-to-target data validations as well as anomaly detection Qualifications And Experience Requirements Bachelor’s degree/master's degree/advanced degree in computer science, statistics, applied mathematics, data management, information systems, information science or related field Expertise and excellent understanding of Snowflake Internals and integration of Snowflake with other data processing and reporting technologies Preferred experience in working with data science teams in refining and optimizing data science and machine learning models and algorithms Full Lifecycle Data Warehouse, Data Mart Development experience is a big plus Agile Software development methodologies Preferred experience with any automation tool such as AutoSys, Cntl-M. Minimum 10 years of work experience in data management disciplines, including data integration, modeling, optimization and data quality, and/or other areas directly relevant to data engineering responsibilities and tasks. Minimum 2 years designing and implementing a fully operational production grade large scale data solution on Snowflake Data Warehouse Minimum 10 years of hands on experience designing and implementing production grade data warehousing solutions on large scale databases such as SQL Server, Oracle or DB2 5+ years data pipeline development experience with Informatica Powercenter and IBM DataStage 3+ years of experience with advanced analytics tools for Object-oriented/object function scripting using languages such as R, Python, Java, C++, Scala, others 3+ years of experience with Shell/Perl Scripting 5+ years of experience with popular database programming languages including SQL, PL/SQL (required), others for relational databases and certifications on upcoming NoSQL/Hadoop oriented databases (preferred) like MongoDB, Cassandra, others for nonrelational databases Show more Show less | K26: Data Engineering, Data Pipeline Design, Data Pipeline Construction, Data Pipeline Implementation, Data Analytics, Data Governance, Data Security, Reusable Data Pipelines, Automation, Metadata Management, Data Integration, Data Management, Snowflake, Data Science, Machine Learning, Agile Development, AutoSys, CntlM, Informatica Powercenter, IBM DataStage, R, Python, Java, C++, Scala, Shell Scripting, Perl Scripting, SQL, PL/SQL, MongoDB, Cassandra
A27: Job Opening for Senior Data Solutions Engineer - backfill - Remote | B27: Steneral Consulting | C27: United States | D27: https://www.linkedin.com/jobs/view/job-opening-for-senior-data-solutions-engineer-backfill-remote-at-steneral-consulting-3657140007 | E27: 45277 | F27: Inverell | G27: Australia | H27: Mid senior | I27: Remote | J27: Hi, Please find attached Job Description. If you are interested please do share with me your updated resume or call me on "3025492448". Title:- Senior Data Solutions Engineer - backfill Location:- Miami, FL Duration:- 6+ Months Visa:- Citizen, GC Interview Mode:- Video Description remote role Need last 6 of SSN, Full DOB and LinkedIn Job Description The Senior Data Solutions Engineer is responsible for building, managing, and optimizing complex reusable enterprise data pipelines effectively and in a timely manner through the development lifecycle to be used by internal consumers, such as business/data analysts and data scientists. Additionally, this role will operate in a fast pace environment working closely with the Data Science and Business teams on Revenue Management initiatives which concentrates in building data solutions, curated data to enable intelligent pricing automation, which relies on machine-learning and data-derived business rules. The Senior Engineer would use both technical and analytical skills to understand and solve business problems using available resources and current technology stack, while ensuring data governance and data security compliance. Create and maintain technical design documentation Gather and document business requirements, data mapping and designing Create, build, and maintain complex data pipelines from disparate sources that meet functional / non-functional business requirements Create, maintain, and reuse existing ETL/ELT processes, employing a variety of data integration and data preparation tools Mentor engineers in finding optimal and efficient solutions for designing, preparing, and storing data for analytical and operational use cases. Identify, design, and implement internal process improvements: automating manual processes, optimizing data delivery, re-designing pipelines for greater scalability, etc. Work with stakeholders including Product, Data and Business teams to assist with data-related technical issues and support their data needs Create datasets for: (1) operational reports, key performance indicators/metrics, or other insights into current organizational activities, (2) analytics and data science to provide the ability to uncover the answers to major questions that help organizations make objective decisions and/or gain a competitive edge Write, debug and implement complex queries involving multiple tables or databases across platform(s) Collaborate with the Enterprise Architecture team to ensure alignment on data standards and processes Work with data and analytics experts to strive for greater functionality in data systems Manages and develops data processing and assigns customers to marketing segments in the CDP; using demographic data, behavioral data, and intent signals and works with data scientists to incorporate machine learning outcomes into the overall customer segmentation model Required Skills Significant experience in using best practices in designing, building and managing data pipelines that require data transformations as well as metadata and workload management Significant experience in working with large, heterogeneous datasets in building and optimizing data pipelines, pipeline architectures and integrated datasets using traditional and new data integration technologies (such as ETL, ELT, data replication, change data captures, message-oriented data movement, API design, stream data integration and data virtualization) Significant experience with streaming technologies (Kafka, Pubsub, Kinesis) and log-based architectures and experience writing batch and stream processing jobs (i.e. Apache Beam, Google Cloud DataFlow, Apache Spark, Apache Storm) Significant experience in performing root cause analysis on internal and external data and processes to identify issues and opportunities for improvement Expert level knowledge with programming languages including SQL, PL/SQL, T-SQL Expert level knowledge with relational SQL databases such as Oracle and SQL Server Significant experience with a scripting language & streaming technologies: Python, Java, Scala, Kafka, etc. Experience with NoSQL databases are a plus Experience supporting and working with cross-functional teams in a dynamic environment Required Education Bachelor of Science in Computer Science, Information Technology or equivalent Required Years Of Experience 5+ years of experience in a data/cloud engineering role 5+ years of experience working and creating datasets for a data warehouse 5+ years of experience with ETL development tools, Informatica or Azure Data Factory (ADF) preferred 3+ years of cloud experience, Azure preferred Desired Skills Clear understanding of data modeling patterns (relational and dimensional) Proven ability to collaborate with technical peers Capable of working independently as well as part of a team Strive to provide orientation and direction to junior engineers requiring their expertise Experienced with continuous integration and continuous deployment practices Ability to approach complex problems with creativity and display analytical and problem-solving skills Display curiosity in understanding the data for the specific area of responsibility Knowledge and experience working with agile methodologies and tools (such as Jira) a plus Additional Information Number Of Allowed Submittals Per Vendor 3 Project assignments, allocation % each project, capital % for capital projects: 100% C23-001 - RM Platform and Automation 1 resource will work on CEL RM Automation 1 resource will work on RCI RM Automation Gaurav Verma Talent Acquisition -North America Direct:+1 3025492448 gaurav.verma@steneral.com In my absence please reach out to Mr. Harish Sharma at harish@steneral.com & 302-721-6151 Show more Show less | K27: Data Pipelines, Data Integration, Data Preparation, ETL, ELT, Data Warehousing, Data Modeling, SQL, PL/SQL, TSQL, Oracle, SQL Server, Python, Java, Scala, Kafka, Pubsub, Kinesis, Apache Beam, Google Cloud DataFlow, Apache Spark, Apache Storm, Informatica, Azure Data Factory, Jira, Agile Methodologies
A28: Lead Data Engineer (AWS, Azure, GCP) | B28: CapTech | C28: Chicago, IL | D28: https://www.linkedin.com/jobs/view/lead-data-engineer-aws-azure-gcp-at-captech-3751644354 | E28: 45277 | F28: Inverell | G28: Australia | H28: Mid senior | I28: Remote | J28: Company Description CapTech is an award-winning consulting firm that collaborates with clients to achieve what’s possible through the power of technology. At CapTech, we’re passionate about the work we do and the results we achieve for our clients. From the outset, our founders shared a collective passion to create a consultancy centered on strong relationships that would stand the test of time. Today we work alongside clients that include Fortune 100 companies, mid-sized enterprises, and government agencies, a list that spans across the country. Job Description CapTech Data Engineering consultants enable clients to build and maintain advanced data systems that bring together data from disparate sources in order to enable decision-makers. We build pipelines and prepare data for use by data scientists, data analysts, and other data systems. We love solving problems and providing creative solutions for our clients. Cloud Data Engineers leverage the client’s cloud infrastructure to deliver this value today and to scale for the future. We enjoy a collaborative environment and have many opportunities to learn from and share knowledge with other developers, architects, and our clients. The Value You Deliver (or What You’ll Do) Be trusted advisor to customers with best practices, methodologies, and technologies to implement data engineering solutions. Design, implement, and maintain modern data pipelines to deliver optimal solutions utilizing appropriate cloud technologies. Partner with product owners and business SMEs to analyze customer requirements and provide a supportable and sustainable engineered solution. Provide technical leadership and collaborate within and across teams to ensure that the overall technical solution is aligned with the customer needs. Stay current with the latest cloud technologies, patterns, and methodologies; share knowledge by clearly articulating results and ideas to key stakeholders. Qualifications Experience building/operating highly available distributed systems of data extraction, ingestion, and processing large data sets 5+ years of experience delivering data engineering solutions on cloud platform 5+ years of experience implementing modern designs using at least one cloud-based solution/platform (AWS, Azure, GCP) Advanced level proficiency with at least one ETL / Data Orchestration technology (Azure Data Factory, SSIS, Informatica, Alteryx, Ab Initio, Pentaho, Talend, Matillion) Experience cloud-based data warehousing and data lake solutions like Snowflake, Redshift, Databricks 5+ years of experience with SQL or NoSQL database (PostgreSQL, MySQL, SQL server, Oracle, Aurora, Presto, BigQuery) Expertise with SQL, database design/structure and data structure (star, snowflake schemas, de/normalized designs) 5+ years of experience with at least one programming language (Python, Java, R, C / C# / C++, Shell) Familiarity with one or more DevOps tools (git, Jenkins, CI/CD, Jira) Fundamental understanding of big data, open source, and data streaming concepts Ability to think strategically and provide recommendations utilizing traditional and modern architectural components based on business needs Experience providing technical leadership and mentoring other engineers in data engineering space Cloud certification on any platform a plus Additional Information We want everyone at CapTech to be able to envision a lasting and rewarding career here, which is why we offer a variety of career paths based on your skills and passions. You decide where and how you want to develop, and we help get you there with customizable career progression and a comprehensive benefits package to support you along the way. Alongside our suite of traditional benefits encompassing generous PTO, health coverage, disability insurance, paid family leave and more, we’ve launched extended benefits to help meet our employees’ needs. CapFlex – Employee-first mentality that supports a remote and hybrid workforce and empowers daily flexibility while servicing our clients Learning & Development – Programs offering certification and tuition support, digital on-demand learning courses, mentorship, and skill development paths Modern Health –A mental health and well-being platform that provides 1:1 care, group support sessions, and self-serve resources to support employees and their families through life’s ups and downs Carrot Fertility –Inclusive fertility and family-forming coverage for all paths to parenthood – including adoption, surrogacy, fertility treatments, pregnancy, and more – and opportunities for employer-sponsored funds to help pay for care Fringe –A company paid stipend program for personalized lifestyle benefits, allowing employees to choose benefits that matter most to them – ranging from vendors like Netflix, Spotify, and GrubHub to services like student loan repayment, travel, fitness, and more Employee Resource Groups – Employee-led committees that embrace and incorporate diversity and inclusion into our day-to-day operations Philanthropic Partnerships – Opportunities to engage in partnerships and pro-bono projects that support our communities. 401(k) Matching – Generous matching and no vesting period to help you continue to build financial wellness CapTech is an equal opportunity employer committed to fostering a culture of equality, inclusion and fairness — each foundational to our core values. We strive to create a diverse environment where each employee is encouraged to bring their unique ideas, backgrounds and experiences to the workplace. For more information about our Diversity, Inclusion and Belonging efforts, click HERE. As part of this commitment, CapTech will ensure that persons with disabilities are provided reasonable accommodations. If reasonable accommodation is needed to participate in the job application or interview process, to perform essential job functions, and/or to receive other benefits and privileges of employment, please contact Laura Massa directly via email lmassa@captechconsulting.com. At this time, CapTech cannot transfer nor sponsor a work visa for this position. Applicants must be authorized to work directly for any employer in the United States without visa sponsorship. Show more Show less | K28: Data Engineering, Data Pipelines, Cloud Technologies, ETL / Data Orchestration, Data Warehousing, Data Lake Solutions, SQL, Database Design, Data Structure, Programming Languages, DevOps Tools, Big Data, Open Source, Data Streaming, Architectural Components, Technical Leadership, Mentoring, Cloud Certification
A29: Lead Data Engineer (AWS, Azure, GCP) | B29: CapTech | C29: Richmond, VA | D29: https://www.linkedin.com/jobs/view/lead-data-engineer-aws-azure-gcp-at-captech-3751641509 | E29: 45277 | F29: Inverell | G29: Australia | H29: Mid senior | I29: Remote | J29: Company Description CapTech is an award-winning consulting firm that collaborates with clients to achieve what’s possible through the power of technology. At CapTech, we’re passionate about the work we do and the results we achieve for our clients. From the outset, our founders shared a collective passion to create a consultancy centered on strong relationships that would stand the test of time. Today we work alongside clients that include Fortune 100 companies, mid-sized enterprises, and government agencies, a list that spans across the country. Job Description CapTech Data Engineering consultants enable clients to build and maintain advanced data systems that bring together data from disparate sources in order to enable decision-makers. We build pipelines and prepare data for use by data scientists, data analysts, and other data systems. We love solving problems and providing creative solutions for our clients. Cloud Data Engineers leverage the client’s cloud infrastructure to deliver this value today and to scale for the future. We enjoy a collaborative environment and have many opportunities to learn from and share knowledge with other developers, architects, and our clients. The Value You Deliver (or What You’ll Do) Be trusted advisor to customers with best practices, methodologies, and technologies to implement data engineering solutions. Design, implement, and maintain modern data pipelines to deliver optimal solutions utilizing appropriate cloud technologies. Partner with product owners and business SMEs to analyze customer requirements and provide a supportable and sustainable engineered solution. Provide technical leadership and collaborate within and across teams to ensure that the overall technical solution is aligned with the customer needs. Stay current with the latest cloud technologies, patterns, and methodologies; share knowledge by clearly articulating results and ideas to key stakeholders. Qualifications Experience building/operating highly available distributed systems of data extraction, ingestion, and processing large data sets 5+ years of experience delivering data engineering solutions on cloud platform 5+ years of experience implementing modern designs using at least one cloud-based solution/platform (AWS, Azure, GCP) Advanced level proficiency with at least one ETL / Data Orchestration technology (Azure Data Factory, SSIS, Informatica, Alteryx, Ab Initio, Pentaho, Talend, Matillion) Experience cloud-based data warehousing and data lake solutions like Snowflake, Redshift, Databricks 5+ years of experience with SQL or NoSQL database (PostgreSQL, MySQL, SQL server, Oracle, Aurora, Presto, BigQuery) Expertise with SQL, database design/structure and data structure (star, snowflake schemas, de/normalized designs) 5+ years of experience with at least one programming language (Python, Java, R, C / C# / C++, Shell) Familiarity with one or more DevOps tools (git, Jenkins, CI/CD, Jira) Fundamental understanding of big data, open source, and data streaming concepts Ability to think strategically and provide recommendations utilizing traditional and modern architectural components based on business needs Experience providing technical leadership and mentoring other engineers in data engineering space Cloud certification on any platform a plus Additional Information We want everyone at CapTech to be able to envision a lasting and rewarding career here, which is why we offer a variety of career paths based on your skills and passions. You decide where and how you want to develop, and we help get you there with customizable career progression and a comprehensive benefits package to support you along the way. Alongside our suite of traditional benefits encompassing generous PTO, health coverage, disability insurance, paid family leave and more, we’ve launched extended benefits to help meet our employees’ needs. CapFlex – Employee-first mentality that supports a remote and hybrid workforce and empowers daily flexibility while servicing our clients Learning & Development – Programs offering certification and tuition support, digital on-demand learning courses, mentorship, and skill development paths Modern Health –A mental health and well-being platform that provides 1:1 care, group support sessions, and self-serve resources to support employees and their families through life’s ups and downs Carrot Fertility –Inclusive fertility and family-forming coverage for all paths to parenthood – including adoption, surrogacy, fertility treatments, pregnancy, and more – and opportunities for employer-sponsored funds to help pay for care Fringe –A company paid stipend program for personalized lifestyle benefits, allowing employees to choose benefits that matter most to them – ranging from vendors like Netflix, Spotify, and GrubHub to services like student loan repayment, travel, fitness, and more Employee Resource Groups – Employee-led committees that embrace and incorporate diversity and inclusion into our day-to-day operations Philanthropic Partnerships – Opportunities to engage in partnerships and pro-bono projects that support our communities. 401(k) Matching – Generous matching and no vesting period to help you continue to build financial wellness CapTech is an equal opportunity employer committed to fostering a culture of equality, inclusion and fairness — each foundational to our core values. We strive to create a diverse environment where each employee is encouraged to bring their unique ideas, backgrounds and experiences to the workplace. For more information about our Diversity, Inclusion and Belonging efforts, click HERE. As part of this commitment, CapTech will ensure that persons with disabilities are provided reasonable accommodations. If reasonable accommodation is needed to participate in the job application or interview process, to perform essential job functions, and/or to receive other benefits and privileges of employment, please contact Laura Massa directly via email lmassa@captechconsulting.com. At this time, CapTech cannot transfer nor sponsor a work visa for this position. Applicants must be authorized to work directly for any employer in the United States without visa sponsorship. Show more Show less | K29: Data Engineering, Cloud Data Engineering, ETL, Data Orchestration, SQL, NoSQL, Data Warehouse, Data Lake, Snowflake, Redshift, Databricks, DevOps, Git, Jenkins, CI/CD, Jira, Python, Java, R, C, C#, C++, Shell, Linux, Unix, Windows
A30: Senior Data Engineer | B30: Hopscotch Primary Care | C30: United States | D30: https://www.linkedin.com/jobs/view/senior-data-engineer-at-hopscotch-primary-care-3770481737 | E30: 45277 | F30: Inverell | G30: Australia | H30: Mid senior | I30: Remote | J30: About Hopscotch Primary Care At Hopscotch Primary Care, we believe great healthcare should be accessible to all people across all communities. Today, almost 20% of Americans live in a rural community, yet only 11% of physicians practice in those same communities. We are on a mission to transform healthcare in rural America. We provide high-quality primary care tailored to meet the needs of our patients through our robust care model and comprehensive care team, delivering care in our clinics, and across settings, and wrapping resources around the patients who need them most. Our patients and the care teams who serve them sit at the center of everything we do at Hopscotch. Hopscotch Primary Care takes a team approach to serve patient needs and provide the best care possible. Our goal is to provide the care each of us would want for ourselves or for our family members, in the right setting, and at the right time. Today, we are serving thousands of patients in our value-based care model and the number is growing every day. If you want to bring your experience, skill and passion to make a lasting impact in healthcare, we’d like to meet you. About The Role We are looking for a mission-driven Senior Data Engineer to join our early team at a critical and exciting time for the company. In this position, you will play a pivotal role in building out Hopscotch’s data and analytics platform and data team. You will have an opportunity to own end-to-end execution of data products and initiatives that directly impact the care delivery process. You will be part of a skilled, passionate, and collaborative team committed to working together to realize Hopscotch’s ambitious and important vision. Responsibilities Near-term focus areas for this role will include, but are not limited to: Build out and maintenance of the data infrastructure that supports end-user workflows, 3rd party integrations, and analytics needs Support integration of new data (e.g. HIE, ADT feeds) as needed to enhance quality and breadth of information available to clinical care teams Build out and maintenance of data pipelines that drive actionable intelligence Requirements scoping and documentation with key stakeholders to continually improve the design of data products across the company Monitor and maintain data pipeline health from ingest to final data products Contribute to our organizational ontology (i.e. data modeling) Collaborate with product teams to design and build out the backing data and infrastructure for organizational workflows Generate analytic insights, build backend KPIs and other metrics to help provide visibility into company performance towards critical goals ABOUT YOU: You would be a great fit for this position if you have 4+ years of experience in data engineering, preferably in healthcare services, and you are: Knowledgeable about healthcare, preferably in the services/provider sector Results-driven and focus time/resources against the most important priorities Creative in finding solutions to arrive at mutually beneficial outcomes Strategic and can bring a structured, proactive approach to get things done Can quickly develop insights from data, and translate findings into action Demonstrate first-principles approach to understanding and solving new problems Can translate complex concepts, verbally and in writing, and use synthesized communications to collaborate across an organization From a cultural perspective, you are: Thoughtful and can work effectively in a fast-paced, ever-changing environment Constantly seeking ways to simplify and improve how things are done Accountable, holding yourself and others to a high standard Willing to roll up your sleeves to support the work required and collaborate effectively with people of all backgrounds Concise and articulate, drive towards clarity Collaborative, assuming positive intentions Mission-driven, with a passion for serving patients and communities Intellectually curious, with a desire to learn new skills and explore new spaces ADDITIONAL QUALIFICATIONS: Experience shipping production level code and pipelines for data purposes Familiarity with healthcare data sources, interfaces and software including EHR, population health tools, patient portals, and clinical decision support technology Comfortable writing clear, testable python code, with pyspark experience preferred Experience with tools to build re-usable, testable, and maintainable data models (e.g. ontologies) Experience with Airflow, Prefect, or other task execution platforms Experience with data lake solutions such Palantir Foundry, Databricks Comfortable in Docker and on the Unix command line Experience with cloud infrastructure (e.g. AWS) and working with serverless computing services (e.g. Lambda) At Hopscotch Primary Care, we embrace diversity, invest in a culture of inclusion and positivity and encourage all to apply to join our team. You will receive consideration for employment without regard to race, color, religion, gender, gender identity or expression, sexual orientation, national origin, genetics, disability, age, or veteran status. Show more Show less | K30: Data engineering, Healthcare data, Data infrastructure, Data pipelines, Data analytics, Data modeling, Python, Pyspark, Airflow, Prefect, Palantir Foundry, Databricks, Docker, Unix, AWS, Lambda, EHR, Population health tools, Patient portals, Clinical decision support technology
A31: Senior Data Engineer | B31: Nav Technologies, Inc. | C31: Chicago, IL | D31: https://www.linkedin.com/jobs/view/senior-data-engineer-at-nav-technologies-inc-3775324854 | E31: 45277 | F31: Inverell | G31: Australia | H31: Mid senior | I31: Remote | J31: Nav is democratizing small business financing. In other words, we give small business owners access and control. Yes, this challenges the norm, but it means working with curious, purpose driven, dedicated, and inquisitively smart people who push themselves, our company and the community to the next level (and every level after that). We are the people behind the tech. And when it's good, we look for better. We don't over think the value we bring nor spend time trying to revamp mantras. We also do not come up with some crafty way to tell you who we are and what we offer. We are Nav! Here, you'll gain a wealth of experience, learn the tricks of the trade, and work with winners. All companies say people are connected to their mission but in our case our mission and our people are one – it is a way of being not just a cause you are committed to. And since 2013, Nav has holistically and organically developed its own ideology because Nav can only be Nav. We are seeking an innovative and passionate Data Engineer to join our team. In this role you will be responsible for building the data and reporting infrastructure to power our systems, working with our team of engineers, product managers and designers; helping us create a better experience for the millions of Nav Small business users. You'll also work with our business intelligence and data science teams to improve the data platform, ensuring that the entire company is able to make better data-driven decisions. YOU WILL: Building cool stuff by maintaining and fulfilling a technical data engineering roadmap and vision. Creating data and reporting infrastructure by building and optimizing production-grade data pipelines through the use of continuous integration. Exploring data sets for insight and understanding that will help drive great product changes and priority. Communicating results and findings to company audiences of varying technical ability in a clear, engaging manner. Breaking down complex technical concepts into digestible tid-bits. Supporting self-service data pipeline management (ETL) and self-directed learning process. Addressing competing explanations in result validity, and use formal reasoning approaches to avoid bias and miscommunication. Collaboration with Engineering and Data Analysts to identify and design ways to solve critical business problems and ensure funnel optimization. Ability to design, develop, and maintain scalable, reusable code. WHO YOU ARE: You are a driven data engineer with experience working with big data technologies such as Docker, ECS, S3, Redshift, Kafka, and RDS. You have experience with ETL/ELT and data warehousing using tools such as dbt, Azure Data Factory, Matillion and/or Fivetran You love building data-driven products and have expertise in one or more programming languages (ideally Python). You have strong SQL experience, with expert level skill in Postgres, Snowflake and /or AWS Redshift. You're an Apache Airflow practitioner with experience managing cross-DAG dependencies in Airflow. You know how to implement, advocate, and teach agile practices, and adapt them to your people and circumstances, while working in accordance with data ethics & privacy standards. You can consistently evolve data models & data schema based on business and engineering needs. You've developed and extended design patterns, processes, standards, frameworks and reusable components for use in various data engineering functions and areas. Ability to implement systems for tracking data quality and consistency. You're comfortable working directly with all internal data consumers and are eager to share your work through calibrations and organizational product demos. You are committed to quality! And you're someone who's willing to tackle technical debt and constantly evolving our processes to help nav grow. We'd love it if you have a high level understanding of credit scores, ecommerce, and B2B financing. Inclusion at Nav: At Nav, we celebrate what makes our employees unique because the businesses we serve are progressively diverse and distinctly original. Navericks are diverse, side hustlers, immigrants, veterans, queer, and we push generational boundaries. We are college dropouts, PhDs, special needs parents, allies, pet owners and community leaders. Navericks are human. We are committed to upholding a safe, supportive environment where everyone matters. We are committed to making a better future for all of us. We have created a workplace where people of all backgrounds can express their identities authentically. To put it simply, we want you to be proud to be you. Our Compensation Philosophy is simple but powerful: At Nav, we are transparent about our total rewards, including pay, across all levels and roles. We believe great, enduring relationships are grounded in trust and transparency. Compensation shouldn't be a distraction, and employees should understand how pay and career advancement decisions are made. Providing equal pay for equal work is table stakes for being a great place to work. Gender and ethnic inequity should only be something that our children read about in history books. We believe providing Navricks with company ownership, competitive pay, and a range of meaningful benefits is the start of creating a culture where people want to give the best they've got — not because they're simply making money, but because they've fallen in love with our vision, mission, values, and team. During the interview process, your recruiter will be explaining how our rubrics work across all of our total rewards ( base, equity, bonus, perks, and benefit) offerings . The base salary for this role is targeted between $120K - $140K per year. Final offer amount is determined by your proficiencies within this level. Our impact on you: Competitive Pay. Company Ownership. Unlimited Vacation. Benefits Day One. 6 Weeks Paid Parental Leave. Work From Anywhere (yes we were distributed before it was cool). Flexible Work Arrangements. Free Telehealth and Telemental Health For All Employees. Employee Networking and Events. Community Network Groups (women's, PRIDE, culture). Meaningful Perks and Rewards. Learning and Development Opportunities. Pet Insurance. A Naverick's DNA: We look at the future and say "why not"; we see possibilities where others see problems or routines. We show the way ahead and are committed to achieving ambitious goals. We practice straight talk and listen generously to each other with empathy. We value different opinions and point of views. We ensure that we connect outside as well as inside to learn from others and inspire each other. We hold ourselves accountable for delivering results. We choose to not to be a victim of circumstance. We make decisions & take responsibility so that we can act & support each other, rather than adopting defensive, and "finger pointing" behaviors. As leaders we motivate & engage our teams to undertake beyond what they originally thought possible, by developing our teams & creating the conditions for people to grow and empower themselves through enabling & coaching. If you are based in California, we encourage you to read our privacy notice for California residents linked here. Show more Show less
A32: Data Engineer | B32: Motion Recruitment | C32: Los Angeles, CA | D32: https://www.linkedin.com/jobs/view/data-engineer-at-motion-recruitment-3730276350 | E32: 45277 | F32: Inverell | G32: Australia | H32: Mid senior | I32: Remote | J32: Job Description | DOES NOT SUPPORT: C2C OR Sponsorship Our client is a people search engine that utilizes deep web crawlers to aggregate data. Their main goal is to reconnect friends, reunite families, prevent fraud, and their most notable usage of their platform has been connecting adoptees to their biological parents. They are looking for a Data Engineer to work fully remote on their ‘Data Operations Team,’ and help optimize their platform, data pipelines, data extractions, and data preparations. This will involve working with infrastructure built in AWS, including Spark EMR, S3, and DynamoDB. Additionally, this role is going to help build statistical tools, develop unit & stress tests, and create automation in the orchestrating of ETL pipelines. As the role grows you will help in the determining of data governance, data quality, data cleansing, and ETL processes. Overall, you will have huge impact for the only data company that serves millions of users directly. They bolster a transparent culture and are promoters of flexibility and work-life balance. Required Skills & Experience 7 yrs. of experience 5 yrs. of Python experience 5 yrs. of Spark OR PySpark experience Airflow Strong understanding of DAG AWS Computer Science Degree (Highly Preferred) The Offer You Will Receive The Following Benefits 12-15% bonus (50% performance; 50% on company performance) Stock Options Unlimited PTO Sign on Bonus Applicants must be currently authorized to work in the US on a full-time basis now and in the future. Posted By: Connor Hart Show more Show less
A33: Remote Work - Need Sr Data Software Engineer | B33: Steneral Consulting | C33: United States | D33: https://www.linkedin.com/jobs/view/remote-work-need-sr-data-software-engineer-at-steneral-consulting-3735082431 | E33: 45277 | F33: Inverell | G33: Australia | H33: Mid senior | I33: Remote | J33: Job : Sr. Data Software Engineer Location: 100% Remote Duration: 6 month Contract to Hire (USC/ GC Holder ONLY) Top Skills SQL Azure Data Factory DBT ETL work Proven ability to complete projects in a timely manner while clearly measuring progress Strong software engineering fundamentals (data structures, algorithms, async programming patterns, object-oriented design, parallel programming) Strong understanding and demonstrated experience with at least one popular programming language (.NET or Java) and SQL constructs. Experience writing and maintaining frontend client applications, Angular preferred Strong experience with revision control (Git) Experience with cloud-based systems (Azure / AWS / GCP). High level understanding of big data design (data lake, data mesh, data warehouse) and data normalization patterns Demonstrated experience with Queuing technologies (Kafka / SNS / RabbitMQ etc) Demonstrated experience with Metrics, Logging, Monitoring and Alerting tools Strong communication skills Strong experience with use of RESTful APIs High level understanding of HL7 V2.x / FHIR based interface messages. High level understanding of system deployment tasks and technologies. (CI/CD Pipeline, K8s, Terraform). Project/Day To Day Communicate with business leaders to help translate requirements into functional specification Develop broad understanding of business logic and functionality of current systems Analyze and manipulate data by writing and running SQL queries Analyze logs to identify and prevent potential issues from occurring Deliver clean and functional code in accordance with business requirements Consume data from any source, such a flat files, streaming systems, or RESTful APIs Interface with Electronic Health Records Engineer scalable, reliable, and performant systems to manage data Collaborate closely with other Engineers, QA, Scrum master, Product Manager in your team as well as across the organization Build quality systems while expanding offerings to dependent teams Comfortable in multiple roles, from Design and Development to Code Deployment to and monitoring and investigating in production systems. Show more Show less | K33: SQL, Azure, Data Factory, DBT, ETL, Angular, Git, Data structures, Algorithms, Async programming patterns, Objectoriented design, Parallel programming, .NET, Java, Queuing technologies, Kafka, SNS, RabbitMQ, Metrics, Logging, Monitoring, Alerting, RESTful APIs, HL7 V2.x, FHIR, System deployment, CI/CD Pipeline, K8s, Terraform
A34: Software Engineer, Data Warehouse Analytics | B34: Stripe | C34: United States | D34: https://www.linkedin.com/jobs/view/software-engineer-data-warehouse-analytics-at-stripe-3785927124 | E34: 45277 | F34: Inverell | G34: Australia | H34: Mid senior | I34: Remote | J34: Who we are About Stripe Stripe is a financial infrastructure platform for businesses. Millions of companies—from the world’s largest enterprises to the most ambitious startups—use Stripe to accept payments, grow their revenue, and accelerate new business opportunities. Our mission is to increase the GDP of the internet, and we have a staggering amount of work ahead. That means you have an unprecedented opportunity to put the global economy within everyone’s reach while doing the most important work of your career. About The Team The team is responsible for offering data warehouse analytics capabilities for Stripe and the stack is supported by a collection of internally developed services and several popular open source technologies like Trino/Presto, Hive Metastore, etc. The systems we own support all of the data warehouse workloads initiated by both services and by individual Stripes across the company to support various business analytics use cases. We process hundreds of thousands of queries on petabytes of data per day and form the key data serving layer for one of the largest financial data lakes in the world. The team is distributed across the USA. What you’ll do You shall be a key contributor to the evolution of our platform and how Stripe analyzes its vast and ever growing data warehouse, to power ever evolving use-cases around analytics, reporting, fraud, AI/ML training, etc at scale. As a Software Engineer, you’ll be empowered to make decisions with a significant impact on Stripe while making our systems reliable, secure, and a delight to use. Responsibilities Scope and lead large technical projects with enormous impact for Engineers within Stripe Build and maintain the infrastructure which powers the core of Stripe. Directly contribute to core interface design and write code. Work closely with the open source community to identify opportunities for adopting new open source features as well contribute back to the OSS. Plan for the growth of Stripe’s infrastructure. Unblock, support and communicate with internal partners to achieve results. Ensure operational excellence and enable a highly available, reliable and secure Data Warehouse Analytics platform. Who you are We’re looking for someone who meets the minimum requirements to be considered for the role. If you meet these requirements, you are encouraged to apply. The preferred qualifications are a bonus, not a requirement. Minimum Requirements BS or MS in Computer Science or equivalent field and interest in Data. 2-7 years of professional experience writing high quality production level code or software programs. Have experience with distributed SQL query engines like Trino. Experience developing, maintaining and debugging distributed systems built with open source tools. Experience building infrastructure as a product centered around user needs. Experience optimizing the end to end performance of distributed systems. Experience with scaling distributed systems in a rapidly moving environment. Preferred Qualifications Experience coding in Java, Scala, Golang. Experience working with distributed SQL query engine space. Familiarity designing APIs or building developer platforms. Familiarity with cloud-based environments such as AWS. Pay and benefits The annual US base salary range for this role is $172,800 - $233,800. For sales roles, the range provided is the role’s On Target Earnings ("OTE") range, meaning that the range includes both the sales commissions/sales bonuses target and annual base salary for the role. This salary range may be inclusive of several career levels at Stripe and will be narrowed during the interview process based on a number of factors, including the candidate’s experience, qualifications, and location. Applicants interested in this role and who are not located in the US may request the annual salary range for their location during the interview process. Additional benefits for this role may include: equity, company bonus or sales commissions/bonuses; 401(k) plan; medical, dental, and vision benefits; and wellness stipends. Show more Show less | K34: Data Warehouse, Data Analytics, Trino/Presto, Hive Metastore, SQL, Java, Scala, Go, AWS, Cloud Computing, Distributed Systems, Open Source, APIs, Developer Platforms
A35: (Level III Database Engineer- ETL- SSIS, ADF, C#) | B35: Steneral Consulting | C35: United States | D35: https://www.linkedin.com/jobs/view/level-iii-database-engineer-etl-ssis-adf-c%23-at-steneral-consulting-3742301276 | E35: 45277 | F35: Inverell | G35: Australia | H35: Mid senior | I35: Remote | J35: Job : Level III Database Engineer Location: Remote Term: 6+ months Contract to Hire (USC/ GC Holer ONLY) Responsibilities Build and maintain ETL processes in SSIS and Azure Data Factory Engineer scalable, reliable and performant systems to manage data Develop, implement and optimize stored procedures and functions Independently research and analyze data issues and provide automated solutions Implement new technologies to enhance the optimization of current practices Provide valuable suggestions regarding new ideas and technologies Top Skills 7+ years of experience as a Data Engineer 5+ years of experience with ETL tools, both SSIS and Azure Data Factory 3+ years of experience with C# (preferably .NET Core) 1+ years of experience with PowerShell or other demonstrated scripting experience Excellent problem-solving skills. Thorough understanding of T-SQL scripting including but not limited to stored procedures, functions and triggers Proven ability to analyze and provide complex solutions based on business requirements Sense of ownership and pride in your performance and its impact on company success Bachelor’s degree in Computer Science, Management Information Systems, Healthcare-related discipline or related field or equivalent work experience Preferred Skills 1+ years of experience with Snowflake 1+ years of experience with Databricks Master’s degree in above mentioned fields Show more Show less | K35: SSIS, Azure Data Factory, SQL, TSQL, C#, PowerShell, Snowflake, Databricks
A36: Staff Data Engineer | B36: AuditBoard | C36: United States | D36: https://www.linkedin.com/jobs/view/staff-data-engineer-at-auditboard-3732150210 | E36: 45277 | F36: Inverell | G36: Australia | H36: Mid senior | I36: Remote | J36: Who We Are Having surpassed $150M ARR and continuing to grow rapidly, AuditBoard is the leading audit, risk, and compliance platform on the market. More than 40% of the Fortune 500, including 6 of the Fortune 10, leverage our award-winning technology to move their businesses forward with greater clarity and agility. And our customers love us: AuditBoard is top-rated on G2.com and Gartner Peer Insights. At AuditBoard we inspire each other to innovate and are proud of what we are producing. We spend each day thinking of new ways to help our customers and contribute to the greater good of our company and our surrounding communities. We are all about assisting each other and breaking through barriers to create the most loved audit, risk, and compliance platform by our customers. This is how we have become one of the 500 fastest-growing tech companies in North America for the fourth year in a row as ranked by Deloitte! Why This Role is Exciting As a Senior Engineer on the Data Platform team, you will play a crucial role in building and operating the data infrastructure that serves AuditBoard. Your responsibilities will include delivering high-quality results to ensure the data infrastructure's security, compliance, optimization, and automation. You will contribute to our architecture while maintaining a high architectural standard. Key Responsibilities Best practices and guardrails: Champion the best practices for using the data platform. Optimize for cost and performance Data architecture: Evaluate data platform architecture. Build and optimize data services to improve compliance, security, reliability, performance, and resource utilization. Infrastructure automation: Increase reliability and employee productivity. Eliminate human errors through the standardization of processes and Infrastructure as Code (Iac) Data infrastructure monitoring: Monitor the platform's health, reliability, cost, and usage. Operational support: Support the platform users for troubleshooting, configuration, version updates, and feature adoptions. Compliance: Build processes and tools to ensure that the data platform is compliant Security: Identify infrastructure security-relevant actions, tests, and key performance indicators. Enhances the security posture of the data platform, ensuring the protection of data, systems, and assets. Attributes for a Successful Candidate 8+ years of development experience with a focus on architecting cloud data platforms, setting up, managing, and automating the infrastructure of cloud data platforms, including Airflow, Databricks, Spark, and Kafka 8+ years of experience and proficient programming skills in Python or Java/C#. 3 years of programming experience in SQL. 7+ years of developer experience using Infrastructure as Code (IaC) technologies, such as AWS Cloud Formation and Terraform 5+ years of experience maintaining and improving OE of data platforms - service alerting, monitoring, and automation. 3+ years of experience with data compliance and governance. Demonstration of collaboration with the internal compliance team and external auditors in planning and execution of all phases of compliance including risk assessment & scoping. Standardize and automate the compliance process. B.S., M.S., or Ph.D. in Computer Science or equivalent Nice to Have Subject matter expert (SME) in architecting cloud data platforms using Databricks, Snowflake, AWS Lake Formation, or other relevant technologies. SME in big data technologies including Spark, Presto, Airflow, Kafka Work in a startup-like environment building agile products and services Create clear and concise documentation, including diagrams, service descriptions, decisions, and runbooks. Deep knowledge of cloud platforms such as AWS, GCP, Azure Perks* Launch a career at one of the fastest-growing SaaS companies in North America! Live your best life (LYBL)! $200/mo for anything that enhances your life Remote and hybrid work options, plus lunch in the office Comprehensive employee health coverage (all locations) 401K with match (US) or pension with match (UK) Competitive compensation & bonus program Flexible Vacation (US exempt & CA) or 25 days (UK) Time off for your birthday & volunteering Unlimited access to LinkedIn Learning Employee resource groups Stock options Opportunities for team and company-wide get togethers! perks may vary based on eligibility Show more Show less | K36: Apache Airflow, Apache Kafka, Apache Spark, AWS, AWS Cloud Formation, AWS Lake Formation, Azuer, Big Data, Cloud Platforms, Cloud Services, Compliance, Databricks, Data Governance, GCP, Infrastructure as Code, Java, Kafka, MySQL, Python, Security, Snowflake, SQL, Terraform
A37: Sr. Data Engineer - Remote | B37: Get It Recruit - Information Technology | C37: Phoenix, AZ | D37: https://www.linkedin.com/jobs/view/sr-data-engineer-remote-at-get-it-recruit-information-technology-3777842745 | E37: 45277 | F37: Inverell | G37: Australia | H37: Mid senior | I37: Remote | J37: Join a recognized leader in promoting health and well-being! We are currently seeking a skilled and experienced professional to fill a remote position based in the beautiful state of Arizona. The remote work opportunity requires residency within the State of Arizona. Role Overview As a Data Engineer, you will play a crucial role in designing and implementing business intelligence and extract, transform, and load (ETL) solutions. The ideal candidate will bring a wealth of experience in advanced SQL techniques, relational database performance, Big Data technologies, and scripting languages like Python. Key Responsibilities Mentor team members in ETL processes and standards, participating in code reviews. Develop and maintain ETL processes, ensuring data accuracy and quality. Design and implement automated tests, including unit tests and integration tests. Collaborate with other technology teams to define and develop solutions. Research and experiment with emerging Data Integration technologies and tools. Support database clustering, mirroring, and replication among other SQL Server technologies. Participate in the Software Development Life Cycle and adhere to best practices. Analyze, map data, and contribute to the team's knowledge base. Qualifications Required: 4+ years of experience in computer programming, query design, and databases. High-School Diploma or GED in a general field of study. Preferred Bachelor's Degree in Information Technology or related field. 4+ years of experience building and managing complex Data Integration solutions. MS SQL Certification or other certification in current programming languages. Essential Competencies Proficiency in spreadsheet, database, and word processing software. Strong knowledge of business intelligence, programming, and data analysis software. Excellent troubleshooting skills and working knowledge of PowerShell. Effective interpersonal skills and ability to prioritize tasks. Our Commitment We are an equal opportunity employer, fostering a diverse and inclusive workplace. We do not discriminate in hiring or employment based on race, ethnicity, color, religion, sex, sexual orientation, gender identity, national origin, age, disability, protected veteran status, or any other protected group. Thank you for considering this exciting opportunity! Employment Type: Full-Time Show more Show less | K37: SQL, Python, ETL, Data Integration, Big Data, Software Development Life Cycle, Data Analysis, Relational Database, PowerShell, MS SQL, Spreadsheets, Databases, Word Processing
A38: Senior Data Engineer / Remote | B38: Motion Recruitment | C38: Los Angeles, CA | D38: https://www.linkedin.com/jobs/view/senior-data-engineer-remote-at-motion-recruitment-3754633912 | E38: 45277 | F38: Inverell | G38: Australia | H38: Mid senior | I38: Remote | J38: Our client is changing the way we can find our friends and family from around the world. Founded in 2008, they have millions of users per month visiting their platform for various reasons. They are looking for a Senior Data Engineer to join their Data Ops team to come in and make an impact right away. This Senior Data Engineer should have at least 7 years of professional experience woking with Python, PySpark, Airflow, AWS, and have a computer Science Degree. If this is you APPLY NOW! Basic Qualifications (Required Skills & Experience) 6-8 years of experience Python – 5 years of experience Spark – 5 years (Prefer Pyspark) AWS – 2+ years of experience Airflow – 2+ years of experience EMR ETL work SQL Technology degree is important as well! (ex: CS degree) Other Qualifications & Desired Competencies Fully Remote!!! Equity and Bonuses involved You Will Receive The Following Benefits Medical Insurance Dental Benefits Vision Benefits 401(k) Posted By: Casey Ryan Show more Show less | K38: Python, PySpark, Airflow, AWS, EMR, ETL, SQL, Computer Science Degree
A39: REMOTE: Data Engineer //Pay rate: $43.35/hr | B39: Stellar Professionals | C39: United States | D39: https://www.linkedin.com/jobs/view/remote-data-engineer-pay-rate-%2443-35-hr-at-stellar-professionals-3704005282 | E39: 45277 | F39: Inverell | G39: Australia | H39: Mid senior | I39: Remote | J39: Applicant must have 2 years of relevant experience with the following: Hands-on experience with data engineering design and implementation Experience with data modeling design and implementation Hands-on industry experience programming in SQL on relational database platforms (T-SQL and PL/SQL preferred) Hands-on industry experience working with enterprise ETL/ELT tools (Azure Data Factory and Databricks preferred) Hands-on experience with modern programing languages like Python, C#, JavaScript, etc (Python preferred) Hands-on experience with Azure, AWS, and/or GCP cloud platforms (Azure preferred) Bachelor's degree in Computer Science, Data Science, Software Engineering, Information Technology or a similar field Progressive mindset particularly around deployment models and emerging technologies Collaborative team player who is detailed oriented, focused on solution quality and execution Experience with Docker for containerization and Kubernetes for orchestration Show more Show less | K39: Data engineering, Data modeling, SQL, TSQL, PL/SQL, ETL/ELT, Azure Data Factory, Databricks, Python, C#, JavaScript, Azure, AWS, GCP, Docker, Kubernetes
A40: Senior Data Warehouse Engineer | B40: Steneral Consulting | C40: United States | D40: https://www.linkedin.com/jobs/view/senior-data-warehouse-engineer-at-steneral-consulting-3718978112 | E40: 45277 | F40: Inverell | G40: Australia | H40: Mid senior | I40: Remote | J40: Share only 2 profiles Indiana local candidates only with local DL LinkedIn is must Senior Data Warehouse Engineer Indianapolis, IN. Location of candidates: Indiana residents ONLY, no relocation. 12+ Month Contact Remote work schedule Responsibilities Collaborate with various IT teams (data, database, and infrastructure) to analyze the agency's utilization of the data warehouse. Provide guidance and education on warehouse environments using industry standards and best practices. Research leading-edge capabilities within the Indiana Office of Technology's scope and guidelines to determine the optimal solution for the overall environment. Define the technological architectural direction and deliver assessment recommendations. Develop a project/implementation plan for establishing the warehouse, including designing ideal data pipelines and other data and visual interfaces. Oversee the setup of the agency's warehouse environment in alignment with the agency's initiative. Configure and set up Azure Synapse with the correct structure. Collaborate with Data Analyst(s) as necessary to define minimal viable data assets in support of visual needs. Review and provide architectural guidance for all analytic solutions. Advise management on any deficiencies in current tools and approaches related to business initiatives. Required Skills Extensive knowledge of information systems design principles and new systems design techniques. A very strong understanding of current industry standards and best practices used in data and data warehouse development. Extensive knowledge of system and business data applications. Sizable experience in setting up other data warehouse environments. Ability to evaluate the business needs and objectives. Extensive knowledge of policies, standards, procedures, and techniques used for data and application development. Ability to perform problem-solving and analytical analysis on complex issues. High technical competency level in all phases of data analysis and development activities. Willingness to train/educate data team members, DBAs, infrastructure support, and management in effective data warehouse designs/approaches. Proficient in developing project plans, including discovery, development, and implementation. Experience in using ETL tools - Azure Synapse and Azure Data Factory. Ability to manage multiple data development assignments and priorities. Ability to communicate effectively, both orally and in writing. Working knowledge in the above skills must be within the last 6 months. Show more Show less | K40: Data Warehousing, Data Analysis, Azure Synapse, Azure Data Factory, ETL Tools, Data Pipelines, Data Visualization, Business Intelligence, Project Management, Problem Solving, Analytical Analysis, Training and Education, Communication Skills, Data Development, Data Application Development, Data and Application Development Policies, Data and Application Development Standards, Data and Application Development Procedures, Data and Application Development Techniques, Information Systems Design Principles, New Systems Design Techniques, Industry Standards and Best Practices, System and Business Data Applications
A41: Senior Data Engineer - Remote | B41: Get It Recruit - Information Technology | C41: San Mateo, CA | D41: https://www.linkedin.com/jobs/view/senior-data-engineer-remote-at-get-it-recruit-information-technology-3774809543 | E41: 45277 | F41: Inverell | G41: Australia | H41: Mid senior | I41: Remote | J41: We are actively searching for a talented Senior Data Engineering Developer to play a pivotal role in shaping the design, development, scaling, and maintenance of our cutting-edge SaaS infrastructure. Join our dynamic team where you'll collaborate closely with cross-functional experts in Data Science, Engineering, and Product/Business Technology. Your mission: construct robust data infrastructure, streamline processes, and enhance our toolset. Responsibilities Visionary Leadership: Spearhead the vision for Business Intelligence (BI) and Data Warehousing, steering the strategic plan to fruition. Assemble a high-caliber BI and Data Warehouse team, fostering their growth and skill development. Collaboration Cultivate collaborative relationships with Product Managers, Analysts, and Software Engineers to decipher data requirements and deliver impactful solutions. Infrastructure Excellence Architect, construct, oversee, and optimize foundational data infrastructure. Implement a monitoring infrastructure for real-time insights into the status of our data pipelines. Implement and supervise processes that enhance implemented solution performance. Optimize schemas, including partitions, compression, and distribution, to balance costs and performance. Craft bespoke data infrastructure solutions not readily available off-the-shelf. Create and sustain custom data ingestion pipelines and seamless integrations with third-party platforms. Data Quality And Dashboards Champion Data Quality and the creation of high-impact dashboards. Management Define and manage Service Level Agreements (SLAs) for all production datasets and processes. Provide guidance and support to our data team, assisting with design decisions and performance optimization strategies. Qualifications Education: Bachelor's degree in a technical and/or quantitative field of study—e.g., computer science, mathematics, physics, statistics, or equivalent and/or substantial related experience. Experience Remarkable track record of 8+ years in the realm of distributed data technologies. Demonstrable experience in ETL and ELT in cloud SaaS/PaaS infrastructures. Proficiency in serverless Microservices like GCP Cloud Function, AWS Lambda. Hands-on experience on streaming and batch data pipeline. Expertise in databases such as Bigquery, MS SQL on data/domain architecture. Expertise in SQL language to be able to transform raw source data into SQL columns. Experience with GCP solutions such as DataFlow and Pubsub are a huge plus. Understanding and experience in AI/ML platform and pipeline, such as Vertex AI. Employee Benefits Competitive compensation packages including bonus and options. Medical, dental, and vision benefits. Matching 401(K). Paid time off. Telecommuting and remote-work options. Support for continuing education. Team off-sites, social events, annual company events, and frequent extracurricular activities. Unlimited snacks and drinks. Remote work. Employment Type: Full-Time Show more Show less | K41: Data Engineering, Business Intelligence, Data Warehousing, Data Infrastructure, Data Pipelines, Data Quality, Dashboards, Data Integration, Cloud SaaS/PaaS, Microservices, GCP Cloud Function, AWS Lambda, Streaming Data, Batch Data, Bigquery, MS SQL, Data Architecture, SQL, DataFlow, Pubsub, Vertex AI, AI/ML
A42: Senior Data Engineer - $180k-$220k (Snowflake, Coding) | B42: CyberCoders | C42: Chicago, IL | D42: https://www.linkedin.com/jobs/view/senior-data-engineer-%24180k-%24220k-snowflake-coding-at-cybercoders-3766365237 | E42: 45277 | F42: Inverell | G42: Australia | H42: Mid senior | I42: Remote | J42: Permanently Remote in US Job Title: Senior Data Engineer - $180k-$220k + Bonus (Snowflake, Coding) Salary: $180k-$220k Base + Bonus, No Stock, 401k, Benefits Requirements: Expert w/ Snowflake & Coding Ability Based in beautiful New York City, we are a cutting edge ad-tech org for television-based ads. We are founded and owned by T.V.s largest publishers. Our mission is to be bring simplicity & scale to audience based campaigns in television. We're working with over 100 advertisers and anticipating another year of significant growth! As a rapidly growing company (founded in 2017 & up 140% year over year) we've recently elevated our C-Suite Team in preparation for our next stage of growth and are building our Technology, Product, and Operations Executive Teams. We have been in business for 7 years and have around 40 employees. Due to growth, we are actively hiring a Senior Data Engineer with Snowflake experience (ideally certified) Ability to write production level code (ideally JavaScript or Python) Experience building data pipelines from scratch and/or working with APIs Experience with the following is a big plus! Fivetran and/or DBT You will be working with 12 other engineers on the data side + several other technical folks. This role will consist of tasks such as building out data pipelines, data architecture via snowflake, and data modeling. If you have this experience, please apply immediately. We are actively interviewing this week and next for this high profile position. Top Reasons to Work with Us Compensation: $180k-$220k Base + Bonus, No Stock, 401k, Benefits Raid Growth: Founded in 2017 & up 140% year over year Culture: Fast paced, mission driven culture Technology: Cutting edge technology What You Will Be Doing Building data pipelines from scratch Data architecture via Snowflake Data modeling Technical review of everything this group builds. Mange development velocity, team capacity, and backlogs Partner closely with the product team Take on key assignments and delegate as needed Act as the main technical point of contact for engineering Translate technical requirements to the rest of the engineering team What You Need for this Position Must Have Experience Snowflake experience Ability to write production level code (ideally JavaScript or Python) Experience building data pipelines from scratch and/or working with APIs Some Experience With: - Fivetran and/or DBT What's In It for You $180k-$220k Base + Bonus, No Stock, 401k, Benefits 401k Vacation/PTO Medical Dental Vision Bonus 401k Benefits Vacation/PTO Medical Dental Vision Bonus So, if you are a Senior Data Engineer - $180k-$220k + Bonus (Snowflake, Coding) with experience, please apply today! Colorado employees will receive paid sick leave. For additional information about available benefits, please contact Nitu Gulati-Pauly Email Your Resume In Word To Looking forward to receiving your resume through our website and going over the position with you. Clicking apply is the best way to apply, but you may also: Nitu.Gulati-Pauly@cybercoders.com Please do NOT change the email subject line in any way. You must keep the JobID: linkedin : MA5-1745335L569 -- in the email subject line for your application to be considered.*** Nitu Gulati-Pauly - VP of Recruiting - CyberCoders Applicants must be authorized to work in the U.S. CyberCoders is proud to be an Equal Opportunity Employer All qualified applicants will receive consideration for employment without regard to race, color, religion, sex, national origin, disability, protected veteran status, or any other characteristic protected by law. Your Right to Work – In compliance with federal law, all persons hired will be required to verify identity and eligibility to work in the United States and to complete the required employment eligibility verification document form upon hire. CyberCoders will consider for Employment in the City of Los Angeles qualified Applicants with Criminal Histories in a manner consistent with the requirements of the Los Angeles Fair Chance Initiative for Hiring (Ban the Box) Ordinance. Show more Show less | K42: Snowflake, JavaScript, Python, Data pipelines, APIs, Fivetran, DBT, Data architecture, Data modeling, Technical review, Mange development velocity, Team capacity, Backlogs, Partner closely, Product team, Key assignments, Delegate assignments, Main technical point of contact, Engineering, Translate technical requirements
A43: Sr. Data Engineer (REMOTE) | B43: Syrinx Consulting | C43: New York, NY | D43: https://www.linkedin.com/jobs/view/sr-data-engineer-remote-at-syrinx-consulting-3648834182 | E43: 45277 | F43: Inverell | G43: Australia | H43: Mid senior | I43: Remote | J43: Who We Are Working with the leader in digital performance solutions, improving the impression quality and audience impact of digital advertising. Built on best practices, our solutions create value for media buyers and sellers by bringing transparency and accountability to the market, ensuring ad viewability, brand safety, fraud protection, accurate impression delivery and audience quality across campaigns to drive performance. This is a great opportunity to get in a remote role!! Please apply directly to ldavis@syrinx.com Headquartered in New York City, DoubleVerify’s investors include JMI Equity, Institutional Venture Partners, Blumberg Capital, First Round Capital and Genacast Ventures. Learn more at doubleverify.com. Overview DoubleVerify is seeking a data slayer, a one in a thousand DBA that loves to ask questions and be on the cutting edge of Big Data technology. The team is responsible for all technical data aspects of the company’s products. The company’s system is comprised of an extremely scalable, highly-available and rapidly-developing architecture, and includes big-data stores of all types – relational, massively-parallel-processing, and NoSQL. This individual will join a small yet highly capable and motivated team in order to maintain the system’s databases, and develop, integrate and deploy complex new modules – quickly and at scale. What You Will Do Develop and maintain Big Data system (Hadoop, Kafka, Hive, Spark) Maintain the system’s databases (Vertica, SQL Server, MongoDB) Develop, integrate and deploy complex new modules (TSQL, Python, Splunk) Design and support Database infrastructure, with consideration for performance, availability, and specific application requirements. Work closely with other departments on the implementation and deployment of new initiatives Who You Are 5+ years of database development and/or administration. 5+ Experience with Hadoop Big Data eco system and experience with Vertica is a must Software development experience is preferred Fast learner, creative thinker, problem solver. Must love BIG data! Accountable, dedicated and willing to be on-call as needed AdTech experience is a plus! Show more Show less | K43: Hadoop, Kafka, Hive, Spark, Vertica, SQL Server, MongoDB, TSQL, Python, Splunk, Big Data, Relational Database, MassivelyParallelProcessing, NoSQL, Database Infrastructure, Performance, Availability, Application Requirements
A44: AWS Data Engineer | B44: Extend Information Systems Inc. | C44: United States | D44: https://www.linkedin.com/jobs/view/aws-data-engineer-at-extend-information-systems-inc-3652274467 | E44: 45277 | F44: Inverell | G44: Australia | H44: Mid senior | I44: Remote | J44: Hi Partner , I hope you are doing well! We have an opportunity Information Security/ Cyber Security Application Project Manager with one of our clients for Mc Lean, VA. Please see the job details below and let me know if you would be interested in this role. If interested, please send me a copy of your resume, contact details, availability, and a good time to connect with you. Job Title: Information Security/ Cyber Security Application Project Manager Location: Mc Lean, VA Duration: C2C Experience level : 10 hands on experience on financials / budget analysis, tracking actuals, working with leads to address the gaps Job Description Identify business unit requirements, create project and process specifications, facilitate testing, coordinate with project teams and ensure that projects are delivered on-time and within budget Identify process improvements and implement Take ownership of end-to-end project delivery Responsible for acting as the primary interface between a specific business/functional area and their IT partners. Represent the organization as the principal customer contact for projects, light enhancements, and other change initiatives Interact with senior customer personnel on significant technical matters frequently requiring coordination across organizational lines Identify and resolve operational issues with business areas. Develops detailed work plans, schedules, project estimates, resource plans, and status reports. Ability to work independently and effectively with staff at all levels and from multiple divisions. Ability to manage multiple priorities and deadlines. Proven ability to learn new business concepts supporting product and/or business process development. Strong organization and presentation skills. Required Skills And Knowledge At least 9+ years of experience in all aspects of the development and implementation of assigned projects and provides a single point of contact for those projects. At least 9+ years of experience in taking projects from original concept through final implementation. Interfaces with all areas affected by the project including end users, computer services, and client services. At least 6+ years of experience in defining project scope and objectives. PMP is a plus Thanks & Regards Anoop Tiwari Extend Information Systems Cell: - 571 - 386 - 2431 Email: Anoop@extendinfosys.com Address: 44258 Mercure Circle, UNIT 102 A, Sterling VA, USA 20166 Web: www.extendinfosys.com Show more Show less | K44: Information Security, Cyber Security, Project Management, Financials, Budget Analysis, Project Specifications, Testing, Project Delivery, Interface, Customer Contact, Technical Matters, Coordination, Operational Issues, Work Plans, Schedules, Project Estimates, Resource Plans, Status Reports, Communication, Organization, Presentation, PMP
... A51: Data Engineer - Lead | B51: Steneral Consulting | C51: United States | D51: https://www.linkedin.com/jobs/view/data-engineer-lead-at-steneral-consulting-3742583023 | E51: 45277 | F51: Inverell | G51: Australia | H51: Mid senior | I51: Remote | J51: Remote role, someone from GA preferred, if not in GA, then must be from FL, NC, AL, CA, NV, IL, UT, MO, TX, PA, NH, PA Candidates need to take a video screen with prime vendor prior to end client submittal Need 2 strong candidates on this role Need strong knowledge of PySprak. 80% of the role will be using Pyspark. They need to be able to be very hands-on and have experience coding within Pyspark not just enabling the tool. Candidates need to have experience with large-scale projects that take 1-2 years versus small projects or proof of concept. Candidates need to have more thought leadership skills. They have a lot of doers currently and need someone who can help guide the team. Top skills: Pyspark Azure Databricks and/or Data Factory Experience leading and managing offshore teams. ETL Must Have Azure Cloud Azure Data Brick ETL High volumes of data Pyspark Python Experience Leading or managing offshore teams Data en gineer has ownership of designing and developing large scale data solutions. You will have deep technical skills in a variety of technologies to play an important role in developing and delivering proof of concepts and product implementation. Responsibilities Design and develop high performant data ingestion pipelines from multiple sources using Azure Databricks and Azure Data Factory Working with event based streaming technologies to ingest and process data Design and Implement Data Lakehouse Working with other members of the project team to support delivery of additional project components (API interfaces, Search) Evaluating the performance and applicability of multiple tools against customer requirements Working within an Agile delivery / DevOps methodology to deliver proof of concept and production implementation in iterative sprints. Work with contractors to deliver products and services for the bottlers Conduct Pilots with bottlers and measure value Transition successful pilots into commercial applications Ensure design and implementation of technologies that comply with security standards and application architecture principles (in alignment with platform architects and respective review boards) and that consider state of the art data and analytics concepts Review code/solutions developed by team prior to migration to production What makes you a good fit? Strong knowledge of data management principles Experience in building ETL pipelines Hands on experience designing and delivering solutions using the Azure including Azure Storage, Azure Data Factory, PySpark, Python, Databricks, Azure Data Lake, Azure Cosmos DB, Azure Stream Analytics Experience working with structured and unstructured data Experience working in DevOps environment 3+ years of relevant experience Ability to balance high customer orientation and service attitude with business priorities Analytic thinking, and problem-solving skills High energy, with strong will and ambition to learn and work on new things Outstanding proven verbal, written and interpersonal communication skills Ability to adapt quickly to changing product scope and priorities (demand driven) Proven ability to influence and collaborate effectively with cross-functional teams Demonstrates noticeable commitment to foster and preserve a culture of diversity and inclusion by creating environments where people of diverse backgrounds are excited to bring all of who they are and do their best work Constant role model of culture: Integrity, Accountability, Passion, Collaboration, Innovation Bachelor’s degree (or equivalent) Show more Show less | K51: PySpark, Azure Databricks, Data Factory, ETL, Python, Azure Cloud, Azure Data Lake, Azure Cosmos DB, Azure Stream Analytics, DevOps, Data pipelines, Data ingestion, Data processing, Data Lakehouse, Data management principles, Structured data, Unstructured data
A52: Principal Engineer - Vehicle Road Load Data RLD | B52: Seismic Recruitment | C52: Bedford, England, United Kingdom | D52: https://uk.linkedin.com/jobs/view/principal-engineer-vehicle-road-load-data-rld-at-seismic-recruitment-3767657549 | E52: 45277 | F52: Northampton | G52: United Kingdom | H52: Mid senior | I52: Onsite | J52: Principal Engineer - Vehicle Road Load Data (RLD) Permanent, based on site in Bedford S alary: up to £65,000 depending on experience and other benefits including eligibility to take part in the bonus which will target 7.5% of salary at OTE, Life Cover, Healthcare cashback plans and many more. Are you a technical leader? Do you enjoy reviewing test data and developing test procedures? Would you like the experience of traveling in Europe to test in different environments? If "yes"… could this newly created role be the opportunity you’ve been looking for? We’re looking for a Principal Engineer to join a leading Automotive Test facility. The successful Engineer will join a company offering customisable vehicle testing solutions, which include; proving grounds and laboratories for vehicle engineering and homologation for transport, agricultural and defence industries (amongst others!) The Durability and Measurement activity conducts whole vehicle testing on test tracks and public roads. Tests include structural and powertrain durability, corrosion, QA, NVH, road load data, dynamics, and many others. What would the Principal Engineer do? Provide technical guidance and leadership to test engineers Lead/support customer discussions from a technical standpoint Validation of testing methodologies and analysis Develop test procedures to meet ISO17025 standards and maintain uncertainty budgets Develop department capability for upcoming regulatory or industry demands Lead integration and cross-pollination of Durability and Measurement tests in UK, France, Morocco, and Finland Support quotation and specification of new and bespoke test and measurement activities Identify and lead improvement activities Undertake analysis of results, including statements of conformity, opinions, and interpretations To report, review and provide authorisation of results What skills and experience will the Principal Engineer need? Relevant engineering degree or extensive experience in similar field(s) Vehicle testing and development ISO17025 compliance Detailed knowledge and experience in some or all of the following areas would be advantageous Advanced data processing (nCode Glyphworks desirable) Data acquisition and instrumentation (DeweSoft desirable) Strain gauging Wheel force transducers Load cells Accelerometers Fatigue and damage calculation Test profile correlation (road to track, track to track, track to rig) Essential requirements? Willing to undergo a Criminal Disclosure check SC clearance or ability to achieve this (UK national with residency in the UK for the last 5 years) Full UK driving license For further information on this excellent opportunity, please call Kym This advert represents a summary of the full role description. To apply, please submit a copy of your up to date CV clearly indicating your relevant experience. Applicants must have an existing right to work in the UK and evidence of eligibility will be required. Suitable candidates will be contacted. Show more Show less
A53: Installation Supervisor (Data Cables / International Travel) | B53: Ernest Gordon Recruitment | C53: Northampton, England, United Kingdom | D53: https://uk.linkedin.com/jobs/view/installation-supervisor-data-cables-international-travel-at-ernest-gordon-recruitment-3781181401 | E53: 45277 | F53: Northampton | G53: United Kingdom | H53: Mid senior | I53: Onsite | J53: £40,000 - £45,000 + Company Van + (£47k - £52k) OTE + Autonomy Northampton, Northamptonshire Do you have hands on experience installing / removing Data Cables and are looking for a days based, Monday to Friday role covering the globe boasting a no two days are the same, field based role where you will have the autonomy to manage a team of installation engineers and projects? On offer is a days based role where you will be visiting sites nationally and internationally supervising installation projects and engineers within a variety of blue chip telecommunication clients. There is plenty of optional overtime available to boost your earnings and you will be required to stay away occasionally during international install projects. This company are renowned within the telecommunications industry for their professional approach and strong customer service skills. Since their start in 2008 this company has grown exponentially and have gained a sterling reputation for their staff retention and professionality. This role would suit an Installation Engineer or similar with supervisory experience looking for a highly autonomous, days based role travelling the globe with plenty of overtime to boost your earnings and the opportunity to further progress into senior managerial positions. The Role Supervising installation projects and engineers globally Travelling across the world with occasional staying away required Optional overtime available paid at 1.33 on Saturday and 1.5 on Sunday Monday to Friday, 8am - 5pm core hours, 40 hours a week The Person Installation Supervisor / Engineer or similar Experience with data cables or similar Full right to work in the UK Reference Number: BBBH11294 Service, Engineer, Installation, Data, Cables, Mechanical, Leicester, Birmingham, Northampton, Nottingham, Supervisor, Field, Junior, Cambridge, Peterborough, Milton Keynes If you're interested in this role, click 'apply now' to forward an up-to-date copy of your CV. We are an equal opportunities employer and welcome applications from all suitable candidates. The salary advertised is a guideline for this position. The offered remuneration will be dependent on the extent of your experience, qualifications, and skill set. Ernest Gordon Recruitment Limited acts as an employment agency for permanent recruitment and employment business for the supply of temporary workers. By applying for this job, you accept the T&C's, Privacy Policy and Disclaimers which can be found at our website. Contact: Arthur Garvey Reference: Totaljobs/BBBH11294 Job ID: 101700309 Show more Show less | K53: Data Cables, Installation, Engineering, Project Management, Supervisory Experience, Field Service, Technical Service, Customer Service, Telecommunications, Mechanical, Installation Supervisor, Installation Engineer
A54: Data Scientist | B54: Techaxis, Inc | C54: Banbury, England, United Kingdom | D54: https://uk.linkedin.com/jobs/view/data-scientist-at-techaxis-inc-3774785189 | E54: 45277 | F54: Northampton | G54: United Kingdom | H54: Mid senior | I54: Onsite | J54: Our client is a multinational technology company specializing in IT services and consulting. It offers a wide range of solutions, including digital transformation, cloud computing, and cybersecurity. Position: Data Scientist Location: Banbury, England Engagement Type: Full-time Skills: Proficiency in Python with experience in data manipulation and analysis using libraries such as Pandas, Numpy, or Matplotlib. Proficiency in SQL and database management systems like PostgreSQL. Knowledge of AI methodologies. Strong problem-solving skills and ability to work with large datasets and complex models. Strong numeracy. Responsibilities: Utilize advanced statistical and machine learning techniques to analyze timing and car data to extract meaningful insights. Apply AI methodologies to enhance data analysis processes and automate repetitive tasks. Design, implement, and optimize algorithms for data mining, machine learning, and predictive modelling. Collaborate with cross-functional teams to integrate Data Science and AI solutions into existing systems and workflows. Gather requirements from race and performance engineers. Collaborate with other data scientists, software and motorsport engineers to drive projects from conception to completion. Writing and maintaining technical documentation, including user manuals and API documentation Contact Details: babita.hazarika@techaxisinc.com | +1 (571) 655-3890 About us: Techaxis Inc. is headquartered in Northern Virginia, USA. We are ranked #3294 in Inc 5000 and #105 in Inc 5000 DC Metro Series, SWaM, and WBE Certified technology talent search firm. Equal Opportunities Employers: Our clients provide equal opportunities to all its employees and all qualified applicants for employment, without regard to their race, caste, religion, color, ancestry, marital status, sex, age, nationality, disability, and veteran status. Employees of our clients are treated with dignity and in accordance with their policy to maintain a work environment free of sexual harassment, whether physical, verbal, or psychological. Employee policies and practices are administered in a manner that would ensure that in all matters equal opportunity is provided to those eligible and the decisions are merit-based. Show more Show less | K54: Python, Pandas, Numpy, Matplotlib, SQL, PostgreSQL, AI, Machine learning, Data mining, Predictive modeling, Data analysis, Technical documentation, User manuals, API documentation
A55: HR Systems and Data Analyst - 12 months FTC | B55: Wickes | C55: Northamptonshire, England, United Kingdom | D55: https://uk.linkedin.com/jobs/view/hr-systems-and-data-analyst-12-months-ftc-at-wickes-3782766198 | E55: 45277 | F55: Northampton | G55: United Kingdom | H55: Mid senior | I55: Hybrid | J55: We are recruiting a HR Systems and Data Analyst to join our wider HR team in Northampton on a 12 months FTC basis. This role will involve administering and configuring our different HR Systems (e.g. user set up, structure changes), act as a HR systems specialist stakeholder when dealing with escalated support tickets, or managing regular auditing processes and high volume data entry. Key Responsibilities: Administer & maintain governance for HR systems e.g. user set up, hierarchy changes, process user requests in line with HR governance, Supporting with data extraction and distribution. Act as an escalation point to problem solve user issues as part of wider HR Shared Services team Provide HR data and systems specialist knowledge to the wider business, Being solely responsible for audits across our HR Systems and maintaining data integrity. Provide support with processes that impact the full employee life-cycle, such as new joiners. Proactively recognise trends in support tickets and escalating system issues immediately to the HR Systems Senior Analyst. Identify system improvements to increase efficiencies. Complete accurate Data Entry in good time, spot inconsistencies in audits and correcting/managing those as soon as they arise. Follow the correct process for accessing and distributing HR data, liaising with the wider team on their reporting requirements. Improve the Line Manager’s experience by identifying training needs, and maintaining/creating user guides/supporting documentation. What are we looking for: An understanding of the HR employee life-cycle. Experience with Data Entry/Customer Service Experience of working with different HR Systems (HRe ideal but not essential) Experience of working with multiple data sources Awareness of HR processes and practices. Analytical and problem-solving skills High attention to detail Strong Organisation Skills Experience with Pivot Tables/basic formula within Excel/Google Sheets Excellent communication skills to effectively present and explain complex systems processes in a clear and simple way Ability to maintain confidentiality and exercise discretion Committed to delivering good customer service Willing to adapt to change Thrives in a busy environment Maintains high quality of detail during repetitive tasks. What can we offer you? You’ll be supported with fantastic learning and development and have the opportunity to grow and develop your career with us We’ll also equip you with a benefits package that includes Annual bonus Save-as-you-earn scheme Contributory pension scheme Colleague discount Discount platform including savings and cash back at numerous retailers, savings on gym membership, cycle to work scheme Our widely recognised wellbeing strategy is something we’re proud of at Wickes. As part of this, we offer a range of health and wellbeing benefits and support, including an Employee Assistance Programme, financial education & loans, and access to parental, menopause and fertility support. We recognise the value of bringing our teams together to collaborate, support each other and build on our amazing culture. We are also encouraging our teams to work flexibly, with a blend of remote / office working. About Us: Wickes is a multi-channel retailer operating in the home improvement market. With 40 years in industry, Wickes now generates revenue in excess of £1.6Bn across 230 stores delivered by 8,000+ colleagues. But it is the Wickes’ culture that is considered its best kept secret; it’s a collaborative, down to earth, fun and inclusive environment where people feel part of a winning team. All our colleagues come from different backgrounds, but what we all have in common is a determination to succeed and a passion for being the best we can be. If that sounds like you, we’ll make you feel right at home. Please note: All offers of employment are subject to DBS / background checks Vacancy Reference # Please contact us here if you require any adjustments within the application process. If you require any reasonable adjustments at the interview stage you will have an opportunity to inform us when we invite you to interview. Please note, this link is only for reasonable adjustments required - general enquiries, or direct CV applications cannot be accepted via this form. Show more Show less | K55: HR Systems Administration, Data Extraction, Data Distribution, Troubleshooting, Data Integrity, Pivot Tables, Microsoft Excel, Google Sheets, Confidentiality, Customer Service, HR Processes, Data Entry
A56: Senior Data Analyst | B56: CV Consulting Ltd | C56: Bedford, England, United Kingdom | D56: https://uk.linkedin.com/jobs/view/senior-data-analyst-at-cv-consulting-ltd-3782398239 | E56: 45277 | F56: Northampton | G56: United Kingdom | H56: Mid senior | I56: Hybrid | J56: Location: Milton Keynes / Hybrid / Remote Salary: £60-70k, plus bonus, excellent benefits and great company culture CV Consulting have been assigned to recruit an experienced Data Analyst with Insight skills and at least 7 years commercial experience to join a growing performance marketing and digital media agency with exciting plans for growth. They are looking for a curious and diligent individual proficient in Python, MySQL, Tableau, Statistics, and eager to learn and play a key role in pushing them towards higher performance standards. Job Description: They are seeking an experienced Senior Analyst to join a small team (of 3 analysts) and become a crucial reinforcement for many areas of the business. You will be trusted to make meaningful contributions to understanding their marketing activities, billing systems, post signup monetisation, directly influencing company growth and improving user experience. Some example projects you could be working on: Improving budgeting and forecasting systems. Developing reports, either AdHoc or via Tableau to share with and inform the wider team. Performing quality checks with our partner integrations to ensure we are maximising our conversion rates and ROI. Creating automated marketing systems with global ad partners. Analysing features to determine what is impacting outcomes. Utilising machine learning packages to enhance our current ops, or uncover insights previously hidden in the data. To be successful in this role it would be advantageous to have an understanding of online marketing and worked in ecommerce or a marketing agency. Key words: Data Analyst, Data Scientist, Market Analyst, Statistics, Tableau, Power BI, MySQL, Marketing Analysis, Media Buying, Online Marketing, Media Planning, Python, R, Marketing Automation, Demand Generation, Statistics, Insights, ecommerce Show more Show less
A57: Senior Data Architect | TS/SCI | B57: YO HR Consultancy | C57: Springfield, MO | D57: https://www.linkedin.com/jobs/view/senior-data-architect-ts-sci-at-yo-hr-consultancy-3767417101 | E57: 45277 | F57: Spokane | G57: United States | H57: Mid senior | I57: Onsite | J57: Company Overview YO HR CONSULTANCY is a leading HR consulting firm operating in the None industry. We specialize in providing comprehensive human resources solutions to companies of all sizes, helping them achieve their talent acquisition and management goals. Role And Responsibilities We are currently seeking a highly skilled Senior Data Architect who will be responsible for the design and implementation of data architectures that support our clients' business goals. In this role, you will be working on various projects, researching and evaluating sources of information, applying sampling techniques, analyzing statistical information, and utilizing statistical methods to solve industry-specific problems. You will also be responsible for preparing detailed reports, training team members, and designing computer code to improve software and applications. Candidate Qualifications Bachelor's degree in mathematics, statistics, computer science or a related field Minimum 8 years of related data engineering architecture and design Comfort with Linux/Windows command line Minimum 8 years of system administration and/or DevOps environment experience TS/SCI Clearance Required Skills Research and analytical skills Statistical analysis and problem-solving Data interpretation and reporting Training and mentoring Software development and coding Skills: automation solutions,data engineer,statistics,architecture,computer science,data engineering architecture,research,voip phone setup,mathematics,device apis,economics,devops,engineering,linux/windows command line,design,data architecture,statistical methods,computer code,operational metrics,data engineering,data pipelines,sampling techniques,system administration,devops environment Show more Show less | K57: Linux, Windows, Command line, Statistical analysis, Problemsolving, Data interpretation, Reporting, Software development, Coding, Automation, Data engineering, Research, Architecture, Computer science, Mathematics, Economics, DevOps, System administration, Data engineering architecture, Data pipelines, Sampling techniques, Operational metrics
A58: Senior Staff AI Data Engineer | B58: Recruiting from Scratch | C58: Cincinnati, OH | D58: https://www.linkedin.com/jobs/view/senior-staff-ai-data-engineer-at-recruiting-from-scratch-3773087716 | E58: 45277 | F58: Cincinnati | G58: United States | H58: Mid senior | I58: Hybrid | J58: Who is Recruiting from Scratch : Recruiting from Scratch is a premier talent firm that focuses on placing the best product managers, software, and hardware talent at innovative companies. Our team is 100% remote and we work with teams across the United States to help them hire. We work with companies funded by the best investors including Sequoia Capital, Lightspeed Ventures, Tiger Global Management, A16Z, Accel, DFJ, and more. https://www.recruitingfromscratch.com/ This is a hybrid role based in our Palo Alto or San Francisco offices and will require you to be in office Tuesdays and Thursdays. What’s so interesting about this role? We believe that AI can revolutionize the dating industry. Our Data Engineer lead is responsible for building high quality ML datasets at scale, used to train ML models that power AI-centric features. In this pivotal role, you will have the opportunity to build foundational tools and data pipelines to ingest, normalize and clean the valuable data that would be fundamental for our ML engineers to build AI tools including recommendations, LLMs, ads, visual search, growth/notifications, trust and safety. What’s the job? We’re looking for an exceptional data engineer who is passionate about data for AI and values it can bring to our company, Who loves working with data ops at scale; and who is committed to the hard work necessary to continuously improve our ML data pipelines. In this position, you will be responsible for establishing and executing the strategy for our organization’s ML Data Engine, with an initial focus on agile ML Data OPs. This includes identification of infrastructure components and data stack to be used, design and implementation of pipelines between data systems and teams, automation workflows, data enrichment and monitoring tools all for AI models. As a tech lead specialized in data engineering, you are expected to code and contribute to the stack. Responsibilities: Dive into our dataset and design, implement and scale data pre/post processing pipelines of ML models Work on applied ML solutions in the areas of data mining, cleaning, normalizing and modeling Be self-motivated in seeking solutions when the correct path isn’t always known Collaborate with engineers in conceptualizing, planning and implementing data engineering initiatives working with different stakeholders Design and build data platforms & frameworks for processing high volumes of data, in real time as well as batch, that will be used across engineering teams Build data processing streams for cleaning and modeling text data for LLMs Research and evaluate new technologies in the big data space to guide our continuous improvement Collaborate with multi-functional teams to help tune the performance of large data applications Work with Privacy and Security team on data governance, risk and compliance initiatives Work on initiatives to ensure stability, performance and reliability of our data infrastructure What We’ll Love About You Bachelors in Computer Science, Mathematics, Physics, or a related fields 5+ years of experience as a data engineer building production-level pre/post-processing data pipelines for ML/DL models, including 2+ years of technical leadership experience Experience in statistical analysis & visualization on datasets using Pandas or R Experience designing and building highly available, distributed systems of data extraction, ingestion, normalization and processing of large data sets in real time as well as batch, that will be used across engineering teams using orchestration frameworks like Airflow, KubeFlow or other pipeline tools Demonstrated prior experience in creating data pipelines for text data sets NLP/ large language models Ability to produce well-engineered software, including appropriate automated test suites, technical documentation, and operational strategy Excellent coding skills in Python, Java, bash, SQL, and expertise with Git version control Experience using big data technologies (Snowflake, Airflow, Kubernetes, Docker, Helm, Spark, pySpark) Experience with any public cloud environment - AWS, GCP or Azure Significant experience with relational databases and query authoring (SQL) as well as NoSQL databases like DynamoDB etc Experience building and maintaining ETL (managing high-quality reliable ETL pipelines) We’ll really swoon if you have 2+ years of experience of technical leadership in building data engineering pipelines for AI Previous experience in building data pipeline for conversational AI APIs and recommender systems Experience with distributed systems and microservices Experience with Kubernetes and building Docker images Experience with building stream-processing systems, using solutions such as Kafka, Storm or Spark-Streaming Strong understanding of applied machine learning topics Be familiar with legal compliance (with data management tools) data classification, and retention Consistent track record of managing and implementing complex data projects What You'll Love About Us Mission and Impact: We are the world-leading LGBTQ social networking service. Your role will impact the lives of millions of LGBTQ people around the world Multiple Locations: We are hiring someone for this role to be based ideally in San Francisco or Palo Alto Family Insurance: Insurance premium coverage for health, dental, and vision for you and partial coverage for your dependents Retirement Savings: Generous 401K plan with 6% match and immediate vest in the US Compensation: Industry-competitive compensation and eligibility for company bonus and equity programs Queer-Inclusive Benefits: Industry-leading gender-affirming offerings with up to 90% cost coverage, access to Included Health, monthly stipends for HRT, and more Additional Benefits: Flexible vacation policy, monthly stipends for cell phone, internet, wellness, and food, one-time home-office setup stipend, and company-sponsored events Base Pay Range $160,000—$280,000 USD https://www.recruitingfromscratch.com/ Show more Show less | K58: Python, Java, bash, SQL, Pandas, R, Spark, Airflow, KubeFlow, Snowflake, Kubernetes, Docker, Helm, pySpark, AWS, GCP, Azure, DynamoDB, ETL, Kafka, Storm, SparkStreaming, ML, LLMs, NLP
